{"tasks":{"Code Jam \"CV\"":{"validatedName":"codejamcv\"","link":"https://github.com/rolling-scopes-school/tasks/blob/2018-Q3/tasks/codejam-cv.md","status":"Checked"},"Code Jam \"CoreJS\" ":{"validatedName":"codejamcorejs\"","link":"https://github.com/rolling-scopes-school/tasks/blob/2018-Q3/tasks/codejam-corejs.md","status":"Checked"},"Code Jam \"DOM, DOM Events\" ":{"validatedName":"codejamdom,domevents\"","link":"https://github.com/rolling-scopes-school/tasks/blob/2018-Q3/tasks/codejam-notification.md","status":"Checked"},"Markup #1":{"validatedName":"markup1","link":"https://github.com/rolling-scopes-school/tasks/blob/2018-Q3/tasks/markup-2018q3.md","status":"Checking"},"RS Activist - ":{"validatedName":"rsactivist","link":"https://github.com/rolling-scopes-school/tasks/blob/2018-Q3/tasks/rs-school-activist.md","status":"In Progress"},"YouTube":{"validatedName":"youtube","link":"https://github.com/rolling-scopes-school/tasks/blob/2018-Q3/tasks/youtube.md","status":"Checking"},"CodeJam \"Scoreboard\"":{"validatedName":"codejamscoreboard\"","link":"https://github.com/rolling-scopes-school/tasks/blob/2018-Q3/tasks/codejam-scoreboard.md","status":"Checking"},"Game":{"validatedName":"game","link":"https://github.com/rolling-scopes-school/tasks/blob/2018-Q3/tasks/game.md","status":"In Progress"},"Course work":{"validatedName":"coursework","link":"undefined","status":"ToDo"},"Presentation":{"validatedName":"presentation","link":"https://github.com/rolling-scopes-school/tasks/blob/2018-Q3/tasks/presentation.md","status":"In Progress"}},"mentors":{"maximuk":{"name":"sergey maksimuk","github":"https://github.com/maximuk","students":{"andrei-oksentyk":{"github":"https://github.com/andrei-oksentyk","tasks":["codejamcorejs\"","codejamcv\"","markup1","codejamdom,domevents\"","youtube","codejamscoreboard\"","presentation"]},"wertybsd":{"github":"https://github.com/wertybsd","tasks":[]},"halaveika":{"github":"https://github.com/halaveika","tasks":["codejamcv\""]},"liodama":{"github":"https://github.com/liodama","tasks":["codejamcorejs\"","codejamcv\"","markup1","codejamdom,domevents\"","youtube","codejamscoreboard\"","presentation","rsactivist"]},"alexey-1991":{"github":"https://github.com/alexey-1991","tasks":[]},"fyr-fyrrr":{"github":"https://github.com/fyr-fyrrr","tasks":["codejamcorejs\"","codejamcv\"","markup1"]},"redgektor":{"github":"https://github.com/redgektor","tasks":["codejamcorejs\"","codejamcv\"","markup1","codejamdom,domevents\""]},"alexdejko":{"github":"https://github.com/alexdejko","tasks":["codejamcv\""]},"alenashkr":{"github":"https://github.com/alenashkr","tasks":["codejamcorejs\"","codejamcv\"","codejamdom,domevents\"","youtube"]},"uniapi":{"github":"https://github.com/uniapi","tasks":[]},"remziq":{"github":"https://github.com/remziq","tasks":["markup1","codejamcorejs\"","codejamcv\"","codejamdom,domevents\"","codejamscoreboard\"","presentation"]},"temons":{"github":"https://github.com/temons","tasks":["codejamcorejs\""]},"sozonikoleg":{"github":"https://github.com/sozonikoleg","tasks":["codejamcorejs\"","codejamcv\"","markup1","codejamdom,domevents\"","youtube","codejamscoreboard\"","presentation"]}}},"alex-zayats":{"name":"aliaksandr zayats","github":"https://github.com/alex-zayats","students":{"uniorunr":{"github":"https://github.com/uniorunr","tasks":["markup1","codejamdom,domevents\""]},"alexeydavydov":{"github":"https://github.com/alexeydavydov","tasks":[]},"melllivoracapensis":{"github":"https://github.com/melllivoracapensis","tasks":["markup1","codejamdom,domevents\""]},"soulshaker":{"github":"https://github.com/soulshaker","tasks":["markup1","codejamdom,domevents\""]}}},"aliaksandrzahorski":{"name":"akiaksandr zahorski","github":"https://github.com/AliaksandrZahorski","students":{"grenbork":{"github":"https://github.com/grenbork","tasks":[]},"bananovblu":{"github":"https://github.com/bananovblu","tasks":[]},"bmvmarc":{"github":"https://github.com/bmvmarc","tasks":["markup1","codejamcorejs\"","codejamcv\"","codejamdom,domevents\"","youtube","codejamscoreboard\""]},"taukitianin":{"github":"https://github.com/taukitianin","tasks":[]},"deepenguin":{"github":"https://github.com/deepenguin","tasks":[]}}},"pristavka":{"name":"siarhei prystauka","github":"https://github.com/Pristavka","students":{"jamadamur":{"github":"https://github.com/jamadamur","tasks":["codejamcv\"","codejamcorejs\"","markup1","codejamdom,domevents\"","presentation"]},"tsvetlanak":{"github":"https://github.com/tsvetlanak","tasks":[]},"alehdzmitrenka":{"github":"https://github.com/alehdzmitrenka","tasks":[]},"dzhudzhi":{"github":"https://github.com/dzhudzhi","tasks":["codejamcv\"","codejamcorejs\"","markup1","codejamdom,domevents\"","youtube","presentation"]},"nataliasirotko":{"github":"https://github.com/nataliasirotko","tasks":["codejamcv\"","codejamcorejs\"","markup1","codejamdom,domevents\"","presentation"]}}},"dpryshchep":{"name":"dzianis pryshchep","github":"https://github.com/dpryshchep","students":{"kira2023":{"github":"https://github.com/kira2023","tasks":["codejamcv\"","codejamcorejs\"","markup1","codejamdom,domevents\"","youtube"]},"vvsvintsitsky":{"github":"https://github.com/vvsvintsitsky","tasks":["codejamcv\"","codejamcorejs\"","markup1","codejamdom,domevents\"","youtube"]},"molestador":{"github":"https://github.com/molestador","tasks":[]},"kiryllapouski":{"github":"https://github.com/kiryllapouski","tasks":["codejamcv\"","codejamcorejs\"","markup1","codejamdom,domevents\""]}}},"quantum-noise":{"name":"aliaksandr klimau","github":"https://github.com/quantum-noise","students":{"803142":{"github":"https://github.com/803142","tasks":["codejamcv\"","codejamcorejs\"","markup1","youtube"]},"0riac":{"github":"https://github.com/0riac","tasks":["codejamcv\"","codejamcorejs\"","codejamdom,domevents\"","markup1","youtube"]},"terstuyahmaksim":{"github":"https://github.com/terstuyahmaksim","tasks":[]},"nickitasolovei":{"github":"https://github.com/nickitasolovei","tasks":["codejamcv\"","codejamcorejs\"","codejamdom,domevents\"","markup1","youtube","codejamscoreboard\"","presentation"]},"saint-artiom":{"github":"https://github.com/saint-artiom","tasks":[]}}},"ahaurylin":{"name":"artsiom haurylin","github":"https://github.com/ahaurylin","students":{"olgaluk":{"github":"https://github.com/olgaluk","tasks":["codejamcorejs\"","codejamcv\"","markup1","codejamdom,domevents\"","codejamdom,domevents\"","youtube","codejamscoreboard\""]},"groamed":{"github":"https://github.com/groamed","tasks":[]},"grapeperson":{"github":"https://github.com/grapeperson","tasks":[]},"rbarakhvostov":{"github":"https://github.com/rbarakhvostov","tasks":[]}}},"elgrebenchuk":{"name":"elena grebenchuk","github":"https://github.com/elgrebenchuk","students":{"andreiyasinski":{"github":"https://github.com/andreiyasinski","tasks":["codejamcorejs\"","codejamcv\"","markup1","codejamdom,domevents\""]},"duza":{"github":"https://github.com/duza","tasks":[]},"anton23kirienko":{"github":"https://github.com/anton23kirienko","tasks":["codejamcorejs\"","codejamcv\"","codejamcv\"","markup1","codejamdom,domevents\"","presentation","youtube"]},"gandigap":{"github":"https://github.com/gandigap","tasks":[]}}},"yganda":{"name":"andrei furs","github":"https://github.com/yganda","students":{"ishelest":{"github":"https://github.com/ishelest","tasks":[]},"yakgjen":{"github":"https://github.com/yakgjen","tasks":[]},"inanutshell86":{"github":"https://github.com/inanutshell86","tasks":[]},"sffirm":{"github":"https://github.com/sffirm","tasks":[]},"zetrox-x":{"github":"https://github.com/zetrox-x","tasks":[]},"juliasnoww":{"github":"https://github.com/juliasnoww","tasks":[]},"loori-r":{"github":"https://github.com/loori-r","tasks":[]}}},"denisbun":{"name":"dzianis bunchanka","github":"https://github.com/DenisBun","students":{"kvinto1986":{"github":"https://github.com/kvinto1986","tasks":["codejamcv\"","codejamcorejs\"","markup1","codejamdom,domevents\"","youtube","presentation","codejamscoreboard\""]},"maksimaliakhnovich":{"github":"https://github.com/maksimaliakhnovich","tasks":["markup1","codejamcv\"","codejamcorejs\"","codejamdom,domevents\"","youtube","presentation","codejamscoreboard\""]},"superorange":{"github":"https://github.com/superorange","tasks":[]},"yauheni23":{"github":"https://github.com/yauheni23","tasks":["codejamcv\"","codejamcorejs\"","markup1","codejamdom,domevents\"","youtube"]}}},"remapasov":{"name":"rem apasov","github":"https://github.com/remapasov","students":{"frol8612":{"github":"https://github.com/frol8612","tasks":["markup1","codejamdom,domevents\""]},"snowwe":{"github":"https://github.com/snowwe","tasks":["markup1","codejamdom,domevents\""]},"dongor7":{"github":"https://github.com/dongor7","tasks":[]},"zettrix":{"github":"https://github.com/zettrix","tasks":[]},"innazl":{"github":"https://github.com/innazl","tasks":[]}}},"tatsianakhinevich-epam":{"name":"tatsiana khinevich","github":"TatsianaKhinevich-EPAM","students":{"makouskiyan":{"github":"https://github.com/makouskiyan","tasks":[]},"shest28":{"github":"https://github.com/shest28","tasks":[]}}},"andrei-zhuk":{"name":"andrei zhuk","github":"https://github.com/Andrei-Zhuk","students":{"torchik-slava":{"github":"https://github.com/torchik-slava","tasks":["codejamcv\"","codejamcv\"","codejamcorejs\""]},"antihero":{"github":"https://github.com/antihero","tasks":["codejamcv\"","codejamcorejs\"","rsactivist","markup1","codejamdom,domevents\""]},"karpiyeniamv":{"github":"https://github.com/karpiyeniamv","tasks":[]},"kirillzavorotni":{"github":"https://github.com/kirillzavorotni","tasks":["codejamcv\"","codejamcv\"","codejamcorejs\"","markup1","codejamdom,domevents\""]},"makar1227":{"github":"https://github.com/makar1227","tasks":["codejamcv\"","codejamcv\"","codejamcorejs\"","markup1","codejamdom,domevents\""]},"mudreuski":{"github":"https://github.com/mudreuski","tasks":["codejamcv\"","codejamcorejs\"","markup1"]},"artkon":{"github":"https://github.com/artkon","tasks":["codejamcv\""]}}},"nikitzu":{"name":"mikita zhuikou","github":"https://github.com/Nikitzu","students":{"felalag":{"github":"https://github.com/felalag","tasks":[]},"xixex":{"github":"https://github.com/xixex","tasks":["codejamcv\"","codejamcorejs\"","youtube","markup1","codejamdom,domevents\""]},"bumble-bee83":{"github":"https://github.com/bumble-bee83","tasks":[]},"mikhama":{"github":"https://github.com/mikhama","tasks":["codejamcv\"","codejamcorejs\"","markup1","youtube","codejamdom,domevents\"","rsactivist","rsactivist","presentation","codejamscoreboard\""]},"angryivan":{"github":"https://github.com/angryivan","tasks":["codejamcv\"","codejamcorejs\"","codejamdom,domevents\"","presentation"]},"alexandr-savkov":{"github":"https://github.com/alexandr-savkov","tasks":[]},"dimalinnik":{"github":"https://github.com/dimalinnik","tasks":[]}}},"alex-mnsk":{"name":"aliaksei zayats","github":"https://github.com/alex-mnsk","students":{"kozyritskiy":{"github":"https://github.com/kozyritskiy","tasks":["markup1","codejamcv\"","codejamcorejs\"","codejamdom,domevents\"","youtube","presentation","codejamscoreboard\""]},"artyom123":{"github":"https://github.com/artyom123","tasks":[]},"evamaster":{"github":"https://github.com/evamaster","tasks":[]},"elenakhamitsevich":{"github":"https://github.com/elenakhamitsevich","tasks":[]},"nastyalo":{"github":"https://github.com/nastyalo","tasks":["codejamcv\"","codejamcorejs\"","codejamdom,domevents\"","markup1","youtube","presentation","codejamscoreboard\"","presentation"]},"lveliarl":{"github":"https://github.com/lveliarl","tasks":[]},"spinagrblzzz":{"github":"https://github.com/spinagrblzzz","tasks":[]}}},"pavelzaletski":{"name":"pavel zaletski","github":"https://github.com/PavelZaletski","students":{"andddrews":{"github":"https://github.com/andddrews","tasks":["codejamcv\"","codejamcorejs\"","markup1","codejamdom,domevents\"","youtube","presentation"]},"bref987":{"github":"https://github.com/bref987","tasks":["codejamcv\"","codejamcorejs\"","codejamdom,domevents\""]},"sergey496":{"github":"https://github.com/sergey496","tasks":["codejamcv\"","codejamcorejs\"","codejamcorejs\"","markup1","codejamdom,domevents\"","rsactivist","youtube","presentation","codejamscoreboard\""]},"anna-sh":{"github":"https://github.com/anna-sh","tasks":[]},"ilyaryabchinski":{"github":"https://github.com/ilyaryabchinski","tasks":[]}}},"yana95":{"name":"yana zaitsava","github":"https://github.com/yana95","students":{"mikhailmaniuk":{"github":"https://github.com/mikhailmaniuk","tasks":[]},"shakhnovapolina":{"github":"https://github.com/shakhnovapolina","tasks":[]},"yana-bashtyk":{"github":"https://github.com/yana-bashtyk","tasks":["codejamcv\"","codejamcorejs\"","markup1","codejamcorejs\"","codejamdom,domevents\"","youtube","presentation"]},"olganaranovich":{"github":"https://github.com/olganaranovich","tasks":["codejamcv\"","codejamcorejs\"","markup1","youtube","presentation"]}}},"tibmt":{"name":"pavel yukhnevich","github":"https://github.com/tibmt","students":{"kasiama":{"github":"https://github.com/kasiama","tasks":[]},"magiccurlyhair":{"github":"https://github.com/magiccurlyhair","tasks":[]},"iryna-markovich":{"github":"https://github.com/iryna-markovich","tasks":[]},"ivankirsd":{"github":"https://github.com/ivankirsd","tasks":[]},"argaitt":{"github":"https://github.com/argaitt","tasks":[]},"danteboom":{"github":"https://github.com/danteboom","tasks":["codejamcv\"","codejamcorejs\""]},"passhub":{"github":"https://github.com/passhub","tasks":[]}}},"a-yatskevich":{"name":"anton yatskevich","github":"https://github.com/a-yatskevich","students":{"mrdreaml":{"github":"https://github.com/mrdreaml","tasks":["codejamcorejs\"","markup1","codejamdom,domevents\"","codejamscoreboard\"","presentation","youtube"]},"tsypolina":{"github":"https://github.com/tsypolina","tasks":["codejamcorejs\"","markup1","codejamdom,domevents\"","presentation"]},"evgeniy121":{"github":"https://github.com/evgeniy121","tasks":["codejamcv\"","codejamcorejs\"","markup1","codejamdom,domevents\""]},"jadgptw":{"github":"https://github.com/jadgptw","tasks":["codejamcv\"","codejamcorejs\"","markup1","codejamdom,domevents\"","youtube","codejamscoreboard\"","presentation"]}}},"viktoriyavorozhun":{"name":"viktoriya vorozhun","github":"https://github.com/ViktoriyaVorozhun","students":{"toxandreev":{"github":"https://github.com/toxandreev","tasks":[]},"evgeniyaverbiczkaya":{"github":"https://github.com/evgeniyaverbiczkaya","tasks":[]},"martikoscoder":{"github":"https://github.com/martikoscoder","tasks":[]},"mayinmarch":{"github":"https://github.com/mayinmarch","tasks":["codejamcv\"","codejamdom,domevents\"","markup1"]},"christina-ilyushonok":{"github":"https://github.com/christina-ilyushonok","tasks":["codejamcv\"","markup1","codejamcorejs\""]}}},"nikolaiverbitskii":{"name":"nikolai verbitskii","github":"https://github.com/NikolaiVerbitskii","students":{"shanhinpavel":{"github":"https://github.com/shanhinpavel","tasks":["codejamcv\"","codejamcorejs\"","markup1","codejamdom,domevents\"","youtube","presentation"]},"igor82bv":{"github":"https://github.com/igor82bv","tasks":["codejamcv\"","codejamcorejs\"","markup1","codejamdom,domevents\"","youtube","presentation","codejamscoreboard\""]},"klimenkomaksim":{"github":"https://github.com/klimenkomaksim","tasks":[]},"uladzimir-yeudakimovich":{"github":"https://github.com/uladzimir-yeudakimovich","tasks":[]}}},"sijlver":{"name":"igor tsialiuk","github":"https://github.com/sijlver","students":{"metre-ray":{"github":"https://github.com/metre-ray","tasks":["codejamcorejs\"","markup1","codejamdom,domevents\"","youtube","codejamscoreboard\""]},"napro23":{"github":"https://github.com/napro23","tasks":[]},"artur-alexandrov":{"github":"https://github.com/artur-alexandrov","tasks":[]},"overkektus":{"github":"https://github.com/overkektus","tasks":[]},"zhekix":{"github":"https://github.com/zhekix","tasks":[]}}},"ntrukhanovets":{"name":"mikita trukhanavets","github":"https://github.com/ntrukhanovets","students":{"vanyatsar":{"github":"https://github.com/vanyatsar","tasks":[]},"lordshtein":{"github":"https://github.com/lordshtein","tasks":[]},"ekoniuh":{"github":"https://github.com/ekoniuh","tasks":[]},"evpodrezenko":{"github":"https://github.com/evpodrezenko","tasks":["codejamcv\"","codejamcorejs\""]},"cruecer":{"github":"https://github.com/cruecer","tasks":["codejamcv\"","codejamcorejs\""]},"annchapon":{"github":"https://github.com/annchapon","tasks":["codejamcv\"","codejamcorejs\""]}}},"kvtofan":{"name":"kiryl tofan","github":"https://github.com/KVtofan","students":{"thesheepman":{"github":"https://github.com/thesheepman","tasks":[]},"brokorenko":{"github":"https://github.com/brokorenko","tasks":["codejamdom,domevents\""]},"vovakor1":{"github":"https://github.com/vovakor1","tasks":[]},"hentmire":{"github":"https://github.com/hentmire","tasks":["codejamcorejs\"","codejamdom,domevents\"","youtube","presentation"]},"rubahaguy":{"github":"https://github.com/rubahaguy","tasks":["codejamcorejs\"","codejamdom,domevents\"","youtube"]},"egorbudnik":{"github":"https://github.com/egorbudnik","tasks":[]}}},"etatarinovich18":{"name":"katsiaryna tatarynovich","github":"https://github.com/etatarinovich18","students":{"kaleniksasha":{"github":"https://github.com/kaleniksasha","tasks":["codejamcv\"","codejamcorejs\"","markup1"]},"ue4prog":{"github":"https://github.com/ue4prog","tasks":["codejamcv\"","codejamcorejs\"","markup1","codejamdom,domevents\""]},"sk1ngr0s":{"github":"https://github.com/sk1ngr0s","tasks":[]},"alexshumansky":{"github":"https://github.com/alexshumansky","tasks":["codejamcv\"","codejamcorejs\"","markup1","codejamdom,domevents\"","rsactivist","codejamscoreboard\""]},"margoshulpina":{"github":"https://github.com/margoshulpina","tasks":[]}}},"einfachvlad":{"name":"uladzislau tarasenka","github":"https://github.com/einfachvlad/","students":{"aleksei-bulgak-study":{"github":"https://github.com/aleksei-bulgak-study","tasks":["codejamcv\"","codejamcorejs\"","markup1","codejamdom,domevents\"","rsactivist","presentation","youtube","rsactivist","codejamscoreboard\""]},"margharita":{"github":"https://github.com/margharita","tasks":[]},"lazovskyigor":{"github":"https://github.com/lazovskyigor","tasks":[]},"dyatelvudu":{"github":"https://github.com/dyatelvudu","tasks":["codejamcv\"","codejamcorejs\"","markup1","markup1","codejamdom,domevents\"","codejamdom,domevents\"","presentation","codejamscoreboard\"","youtube"]}}},"aliaksandrt":{"name":"aliaksandr tachko","github":"https://github.com/aliaksandrT","students":{"leshich":{"github":"https://github.com/leshich","tasks":[]},"tamefreak":{"github":"https://github.com/tamefreak","tasks":[]},"shutya":{"github":"https://github.com/shutya","tasks":["markup1"]},"dgekaa":{"github":"https://github.com/dgekaa","tasks":[]},"leontyevatatyana":{"github":"https://github.com/leontyevatatyana","tasks":[]},"19alexandr90":{"github":"https://github.com/19alexandr90","tasks":[]}}},"sushchenja":{"name":"dzianis sushchenya","github":"https://github.com/sushchenja","students":{"nightman20104":{"github":"https://github.com/nightman20104","tasks":["codejamcv\"","codejamcorejs\"","markup1"]},"irin-ka":{"github":"https://github.com/irin-ka","tasks":["codejamcv\"","codejamcorejs\"","codejamdom,domevents\"","markup1","presentation","codejamscoreboard\"","youtube"]},"daniil-loban":{"github":"https://github.com/daniil-loban","tasks":["codejamcv\"","codejamdom,domevents\"","markup1","rsactivist","rsactivist","rsactivist","presentation","youtube"]},"misharsweb":{"github":"https://github.com/misharsweb","tasks":[]}}},"sulemanof":{"name":"daniil suleiman","github":"https://github.com/sulemanof","students":{"heaveek":{"github":"https://github.com/heaveek","tasks":["codejamcv\"","markup1","codejamdom,domevents\""]},"olegsabodash":{"github":"https://github.com/olegsabodash","tasks":["codejamcv\"","codejamcorejs\"","markup1","codejamdom,domevents\"","youtube","presentation","codejamscoreboard\""]},"andriva":{"github":"https://github.com/andriva","tasks":[]},"meearlyam":{"github":"https://github.com/meearlyam","tasks":["codejamcv\"","codejamcorejs\""]},"veronikavasilchikova":{"github":"https://github.com/veronikavasilchikova","tasks":[]}}},"nsubbot":{"name":"mikita subbot","github":"https://github.com/nsubbot","students":{"eughene-cherepov":{"github":"https://github.com/eughene-cherepov","tasks":["codejamcv\"","codejamcorejs\"","codejamcorejs\"","codejamcorejs\"","presentation"]},"moraviin":{"github":"https://github.com/moraviin","tasks":["codejamcv\"","codejamcorejs\"","presentation"]},"petriken":{"github":"https://github.com/petriken","tasks":["codejamcv\"","codejamcorejs\"","presentation"]},"luzko":{"github":"https://github.com/luzko","tasks":[]},"finnibyh":{"github":"https://github.com/finnibyh","tasks":["codejamcv\"","codejamcorejs\"","presentation"]},"aglayasv":{"github":"https://github.com/aglayasv","tasks":[]},"tonykosmos":{"github":"https://github.com/tonykosmos","tasks":[]}}},"stpnvntn":{"name":"anton stsiapanau","github":"https://github.com/stpnvntn","students":{"metalhammer4":{"github":"https://github.com/metalhammer4","tasks":["codejamcv\"","codejamcorejs\"","markup1","codejamdom,domevents\""]},"rudlevsky":{"github":"https://github.com/rudlevsky","tasks":[]},"ostik266":{"github":"https://github.com/ostik266","tasks":["codejamcorejs\"","codejamcv\"","markup1","codejamdom,domevents\""]},"katekosushkina":{"github":"https://github.com/katekosushkina","tasks":["codejamcv\"","codejamcorejs\"","markup1"]},"viki-klipp":{"github":"https://github.com/viki-klipp","tasks":[]},"anyalenko":{"github":"https://github.com/anyalenko","tasks":[]},"northingvar":{"github":"https://github.com/northingvar","tasks":[]}}},"shuspes":{"name":"alexander spesivtsev","github":"https://github.com/shuspes","students":{"prudnikov888":{"github":"https://github.com/prudnikov888","tasks":[]},"sergeyskakun":{"github":"https://github.com/sergeyskakun","tasks":["codejamcorejs\"","codejamdom,domevents\"","youtube","codejamscoreboard\""]},"petersonby":{"github":"https://github.com/petersonby","tasks":[]},"aliaksandrposakh":{"github":"https://github.com/aliaksandrposakh","tasks":["codejamdom,domevents\"","markup1","presentation","codejamscoreboard\"","youtube"]},"formalinfigs":{"github":"https://github.com/formalinfigs","tasks":[]}}},"mikalai-sokarau":{"name":"mikalai sokarau","github":"https://github.com/mikalai-sokarau","students":{"f8b23lef":{"github":"https://github.com/f8b23lef","tasks":["codejamcorejs\"","codejamcv\"","codejamdom,domevents\"","markup1","youtube","presentation","codejamscoreboard\""]},"yrapank":{"github":"https://github.com/yrapank","tasks":["codejamcorejs\""]},"jenia-shibkova":{"github":"https://github.com/jenia-shibkova","tasks":[]},"magerrrr":{"github":"https://github.com/magerrrr","tasks":[]},"danila211":{"github":"https://github.com/danila211","tasks":[]},"juliazakharik":{"github":"https://github.com/juliazakharik","tasks":[]}}},"kseniyasmorshchek":{"name":"kseniya smorshchek","github":"https://github.com/KseniyaSmorshchek","students":{"ltcolumbo":{"github":"https://github.com/ltcolumbo","tasks":[]},"veterkam":{"github":"https://github.com/veterkam","tasks":[]},"yurychajkou":{"github":"https://github.com/yurychajkou","tasks":["codejamcorejs\"","markup1"]},"catrieona":{"github":"https://github.com/catrieona","tasks":["codejamcorejs\"","markup1","codejamcv\"","presentation","codejamdom,domevents\"","youtube"]},"ankorbay":{"github":"https://github.com/ankorbay","tasks":["codejamcorejs\"","markup1","codejamcv\""]}}},"arhigod":{"name":"arseni shynkarenka","github":"https://github.com/arhigod","students":{"nastya-ropot":{"github":"https://github.com/nastya-ropot","tasks":["codejamcorejs\"","codejamcv\"","codejamdom,domevents\"","markup1","markup1","youtube","youtube","youtube","presentation"]},"mozgoen":{"github":"https://github.com/mozgoen","tasks":["codejamcorejs\"","codejamcv\"","codejamdom,domevents\"","markup1","youtube","presentation","codejamscoreboard\""]},"hellsingi":{"github":"https://github.com/hellsingi","tasks":["codejamcorejs\"","codejamcv\"","codejamdom,domevents\"","markup1","youtube","youtube","presentation","youtube","codejamscoreboard\""]},"yeilya":{"github":"https://github.com/yeilya","tasks":[]},"polotenchik":{"github":"https://github.com/polotenchik","tasks":["codejamcorejs\"","codejamcv\"","codejamdom,domevents\"","markup1","markup1","youtube","codejamscoreboard\""]},"tshkursk":{"github":"https://github.com/tshkursk","tasks":[]}}},"atzkdeff":{"name":"andrei shyliahin","github":"https://github.com/Atzkdeff","students":{"olegkizz":{"github":"https://github.com/olegkizz","tasks":[]},"lazouskikiryl":{"github":"https://github.com/lazouskikiryl","tasks":["codejamcv\"","markup1"]},"dimabog22":{"github":"https://github.com/dimabog22","tasks":["codejamcv\"","codejamcorejs\"","markup1"]},"bigshaqmnh":{"github":"https://github.com/bigshaqmnh","tasks":["codejamcv\"","codejamcorejs\"","markup1","codejamdom,domevents\"","presentation","youtube"]},"antonnaumchik":{"github":"https://github.com/antonnaumchik","tasks":[]}}},"shutya":{"name":"dzianis shutsikau","github":"https://github.com/Shutya","students":{"kirillstarlight":{"github":"https://github.com/kirillstarlight","tasks":[]},"waldemar999":{"github":"https://github.com/waldemar999","tasks":["codejamcv\"","codejamdom,domevents\""]},"kushnerevich":{"github":"https://github.com/kushnerevich","tasks":[]},"igarok91":{"github":"https://github.com/igarok91","tasks":[]},"aliakseibabko":{"github":"https://github.com/aliakseibabko","tasks":["codejamcorejs\"","codejamdom,domevents\"","presentation"]},"gleb7raul":{"github":"https://github.com/gleb7raul","tasks":["codejamcv\"","codejamcorejs\"","markup1","codejamdom,domevents\"","youtube","presentation","codejamscoreboard\"","presentation","youtube"]},"zhekaprb":{"github":"https://github.com/zhekaprb","tasks":[]}}},"klim711":{"name":"klim shuplenkou","github":"https://github.com/Klim711","students":{"dmlaziuk":{"github":"https://github.com/dmlaziuk","tasks":[]},"vladqqqqoo":{"github":"https://github.com/vladqqqqoo","tasks":["codejamcv\"","codejamcorejs\"","markup1","codejamdom,domevents\""]},"globalbobone":{"github":"https://github.com/globalbobone","tasks":[]},"wushukms":{"github":"https://github.com/wushukms","tasks":[]}}},"elenashokhanepam":{"name":"elena shokhan","github":"https://github.com/ElenaShokhanEPAM","students":{"aborisenok":{"github":"https://github.com/aborisenok","tasks":["codejamcorejs\"","codejamcv\"","markup1","codejamdom,domevents\"","youtube","codejamscoreboard\"","presentation"]},"valiantsinlopan":{"github":"https://github.com/valiantsinlopan","tasks":["codejamcorejs\"","codejamcv\"","markup1","codejamdom,domevents\"","youtube","presentation","codejamscoreboard\""]},"egormiwa1":{"github":"https://github.com/egormiwa1","tasks":["codejamcorejs\"","markup1","codejamcv\"","codejamcv\"","codejamdom,domevents\"","codejamdom,domevents\"","youtube","codejamscoreboard\""]},"foxygirl44":{"github":"https://github.com/foxygirl44","tasks":[]}}},"manuminsk":{"name":"andrei shelenhouski","github":"https://github.com/manuminsk","students":{"smajlichak":{"github":"https://github.com/smajlichak","tasks":[]},"zm1try":{"github":"https://github.com/zm1try","tasks":["codejamcv\"","codejamcorejs\"","markup1","codejamdom,domevents\"","youtube","presentation","codejamscoreboard\""]},"jstrr":{"github":"https://github.com/jstrr","tasks":[]},"kirill82":{"github":"https://github.com/kirill82","tasks":["codejamcv\"","codejamcorejs\"","markup1","codejamdom,domevents\"","youtube","presentation"]},"blackcat1397":{"github":"https://github.com/blackcat1397","tasks":[]}}},"davojta":{"name":"dzianis sheka","github":"https://github.com/davojta","students":{"pavalescoba":{"github":"https://github.com/pavalescoba","tasks":["markup1","codejamcorejs\"","codejamcv\"","codejamdom,domevents\"","presentation","youtube"]},"kashapov":{"github":"https://github.com/kashapov","tasks":[]},"michaeldaineka":{"github":"https://github.com/michaeldaineka","tasks":[]},"lesechka":{"github":"https://github.com/lesechka","tasks":["codejamcorejs\"","markup1","codejamcv\"","presentation","codejamdom,domevents\"","youtube"]},"vasiliyrepin":{"github":"https://github.com/vasiliyrepin","tasks":["codejamdom,domevents\"","codejamcv\"","codejamcorejs\"","presentation","markup1","codejamscoreboard\""]},"mike80by":{"github":"https://github.com/mike80by","tasks":["markup1","codejamcv\"","codejamdom,domevents\"","codejamcorejs\"","youtube","presentation","codejamscoreboard\""]},"sergeyshestak":{"github":"https://github.com/sergeyshestak","tasks":[]},"victorbelikov":{"github":"https://github.com/victorbelikov","tasks":["codejamcv\"","codejamcorejs\"","markup1","codejamdom,domevents\"","youtube","presentation","codejamscoreboard\""]},"auseika":{"github":"https://github.com/auseika","tasks":["markup1","codejamdom,domevents\"","codejamcorejs\"","codejamcv\"","youtube","rsactivist","rsactivist","presentation","codejamscoreboard\""]},"iharpadbiarezski":{"github":"https://github.com/iharpadbiarezski","tasks":["markup1","codejamdom,domevents\"","codejamcv\"","codejamcorejs\""]}}},"naooki":{"name":"yahor sheinikau","github":"https://github.com/Naooki","students":{"eveshad":{"github":"https://github.com/eveshad","tasks":["codejamcorejs\"","codejamcv\"","markup1","codejamdom,domevents\""]},"mbulldozer":{"github":"https://github.com/mbulldozer","tasks":["codejamcorejs\"","codejamcv\"","markup1","codejamdom,domevents\"","youtube","codejamscoreboard\"","presentation"]},"starkary":{"github":"https://github.com/starkary","tasks":[]},"olgalazarevich":{"github":"https://github.com/olgalazarevich","tasks":["codejamcorejs\"","codejamcv\"","markup1","codejamdom,domevents\"","youtube"]},"holeil":{"github":"https://github.com/holeil","tasks":[]}}},"forkollaider":{"name":"tsikhan shcharbakou","github":"https://github.com/forkollaider","students":{"aalexsoloveiko":{"github":"https://github.com/aalexsoloveiko","tasks":[]},"sergeibel":{"github":"https://github.com/sergeibel","tasks":[]},"do100han":{"github":"https://github.com/do100han","tasks":[]},"zhecha":{"github":"https://github.com/zhecha","tasks":["markup1","codejamdom,domevents\""]},"odegay":{"github":"https://github.com/odegay","tasks":[]},"mill9r":{"github":"https://github.com/mill9r","tasks":[]}}},"hirurgo":{"name":"mikalai shchakatsikhin","github":"https://github.com/Hirurgo","students":{"tanya98":{"github":"https://github.com/tanya98","tasks":[]},"mixniuk":{"github":"https://github.com/mixniuk","tasks":[]},"xseniia":{"github":"https://github.com/xseniia","tasks":["codejamcv\"","codejamcorejs\"","codejamdom,domevents\"","markup1","youtube","presentation"]},"nataligleb":{"github":"https://github.com/nataligleb","tasks":[]},"valeriyager":{"github":"https://github.com/valeriyager","tasks":["codejamcorejs\"","codejamcv\"","markup1","codejamdom,domevents\"","youtube","presentation","codejamscoreboard\""]}}},"asharapa":{"name":"anton sharapa","github":"https://github.com/asharapa","students":{"mentos2805":{"github":"https://github.com/mentos2805","tasks":[]},"sergeybandar":{"github":"https://github.com/sergeybandar","tasks":[]},"alexanderkononok":{"github":"https://github.com/alexanderkononok","tasks":["codejamcv\"","codejamcorejs\"","codejamdom,domevents\""]},"mrmars20":{"github":"https://github.com/mrmars20","tasks":["markup1","codejamdom,domevents\""]}}},"cyrilshalyapin":{"name":"kiryl shaliapin","github":"https://github.com/CyrilShalyapin","students":{"sergeyakzhik":{"github":"https://github.com/sergeyakzhik","tasks":[]},"kulinar310":{"github":"https://github.com/kulinar310","tasks":["markup1"]},"cropotan":{"github":"https://github.com/cropotan","tasks":["markup1"]},"vitalydmitriev":{"github":"https://github.com/vitalydmitriev","tasks":[]},"philipsh":{"github":"https://github.com/philipsh","tasks":["markup1"]},"vero-nika":{"github":"https://github.com/vero-nika","tasks":[]},"vladsemenik":{"github":"https://github.com/vladsemenik","tasks":["markup1"]}}},"ilyalisitsin":{"name":"illia sauchuk","github":"https://github.com/IlyaLisitsin","students":{"meller96":{"github":"https://github.com/meller96","tasks":["codejamcorejs\"","codejamcv\""]},"ogurez":{"github":"https://github.com/ogurez","tasks":["codejamcorejs\"","codejamcv\"","markup1","codejamdom,domevents\"","youtube","presentation"]},"mrlapka":{"github":"https://github.com/mrlapka","tasks":["codejamcorejs\"","codejamcv\"","markup1","codejamdom,domevents\"","youtube","presentation","codejamscoreboard\""]},"olexxxey":{"github":"https://github.com/olexxxey","tasks":[]},"xelson":{"github":"https://github.com/xelson","tasks":[]},"amoebiusss":{"github":"https://github.com/amoebiusss","tasks":["codejamcorejs\"","codejamcv\"","markup1","codejamdom,domevents\"","rsactivist","youtube","presentation","codejamscoreboard\""]},"megustafather":{"github":"https://github.com/megustafather","tasks":[]}}},"katya-sanko":{"name":"ekaterina sanko","github":"https://github.com/katya-sanko","students":{"kyleshovbb":{"github":"https://github.com/kyleshovbb","tasks":[]},"yabeda79":{"github":"https://github.com/yabeda79","tasks":[]},"sergmi":{"github":"https://github.com/sergmi","tasks":[]},"disa0808":{"github":"https://github.com/disa0808","tasks":["codejamcv\"","codejamcorejs\"","markup1"]},"pulya10c":{"github":"https://github.com/pulya10c","tasks":["codejamcv\"","codejamcorejs\"","markup1","codejamdom,domevents\"","youtube","codejamscoreboard\"","presentation"]}}},"yulia9":{"name":"yuliya samuilik","github":"https://github.com/yulia9","students":{"prometei299":{"github":"https://github.com/prometei299","tasks":["codejamcv\"","codejamcorejs\"","markup1","codejamdom,domevents\"","youtube","presentation"]},"sergeypunko":{"github":"https://github.com/sergeypunko","tasks":[]},"zurzur":{"github":"https://github.com/zurzur","tasks":["codejamcv\"","codejamcorejs\"","markup1","codejamdom,domevents\"","codejamscoreboard\""]},"edaineko":{"github":"https://github.com/edaineko","tasks":[]},"seidou99":{"github":"https://github.com/seidou99","tasks":[]}}},"sambl4":{"name":"dzmitry samuilik","github":"https://github.com/Sambl4","students":{"sches":{"github":"https://github.com/sches","tasks":[]},"simaxa7":{"github":"https://github.com/simaxa7","tasks":["codejamcv\"","codejamcorejs\"","markup1","codejamdom,domevents\"","youtube","rsactivist","presentation","codejamscoreboard\""]},"polinamoiseyenko":{"github":"https://github.com/polinamoiseyenko","tasks":["codejamcv\"","codejamcv\"","codejamcorejs\"","markup1","codejamdom,domevents\"","youtube","presentation","codejamscoreboard\""]},"sashakaralchuk":{"github":"https://github.com/sashakaralchuk","tasks":[]}}},"erutkovsky":{"name":"yauheni rutkouski","github":"https://github.com/erutkovsky","students":{"hecateenitharmon":{"github":"https://github.com/hecateenitharmon","tasks":["codejamcv\"","codejamcorejs\"","markup1"]},"mdgh":{"github":"https://github.com/mdgh","tasks":["codejamcv\"","codejamcorejs\"","markup1","codejamdom,domevents\"","presentation","youtube"]},"mggeroff":{"github":"https://github.com/mggeroff","tasks":[]},"soulos410":{"github":"https://github.com/soulos410","tasks":["codejamcv\"","codejamcorejs\"","markup1"]},"boshka0":{"github":"https://github.com/boshka0","tasks":["codejamcv\"","codejamcorejs\"","markup1","codejamdom,domevents\"","presentation","youtube","codejamscoreboard\""]}}},"rudikaleksandr":{"name":"aliaksandr rudzin","github":"https://github.com/RudikAleksandr","students":{"mrchester":{"github":"https://github.com/mrchester","tasks":[]},"mxwoodie":{"github":"https://github.com/mxwoodie","tasks":[]},"psevkin":{"github":"https://github.com/psevkin","tasks":["codejamcv\"","codejamcorejs\"","markup1","codejamdom,domevents\""]},"alexeevadaria":{"github":"https://github.com/alexeevadaria","tasks":[]},"spiritforest":{"github":"https://github.com/spiritforest","tasks":["codejamcv\"","codejamcorejs\"","codejamcorejs\"","markup1","codejamdom,domevents\"","youtube","presentation"]},"chekni":{"github":"https://github.com/chekni","tasks":["codejamcv\"","codejamcorejs\"","codejamdom,domevents\"","markup1"]},"shymaxer":{"github":"https://github.com/shymaxer","tasks":[]}}},"nikitarudy":{"name":"mikita rudy","github":"https://github.com/NikitaRudy","students":{"sad4itananda":{"github":"https://github.com/sad4itananda","tasks":["codejamdom,domevents\""]},"kalitamih":{"github":"https://github.com/kalitamih","tasks":["codejamcv\"","codejamcorejs\"","markup1","codejamdom,domevents\"","youtube","presentation","codejamscoreboard\""]},"evgenprushk":{"github":"https://github.com/evgenprushk","tasks":[]},"mrstalon":{"github":"https://github.com/mrstalon","tasks":["codejamcv\"","codejamcorejs\"","markup1","codejamdom,domevents\"","rsactivist","youtube","codejamscoreboard\"","presentation"]},"avaprin":{"github":"https://github.com/avaprin","tasks":[]},"haspadarz-padmensku":{"github":"https://github.com/haspadarz-padmensku","tasks":["codejamcorejs\"","codejamcv\"","markup1","codejamdom,domevents\"","youtube","codejamscoreboard\"","presentation"]},"svoboda-rabstvo":{"github":"https://github.com/svoboda-rabstvo","tasks":[]}}},"rianby64":{"name":"andres rios","github":"https://github.com/rianby64","students":{"yaroslav-mig":{"github":"https://github.com/yaroslav-mig","tasks":["markup1","markup1","codejamcorejs\"","codejamdom,domevents\""]},"novikovantony":{"github":"https://github.com/novikovantony","tasks":["markup1","codejamcv\"","codejamcorejs\"","codejamdom,domevents\"","youtube","presentation","codejamscoreboard\""]},"mayblackwood":{"github":"https://github.com/mayblackwood","tasks":["codejamcv\"","codejamcorejs\"","markup1","codejamdom,domevents\""]},"anastminsk":{"github":"https://github.com/anastminsk","tasks":[]},"28halavach":{"github":"https://github.com/28halavach","tasks":[]},"40grivenprog":{"github":"https://github.com/40grivenprog","tasks":[]},"igordive":{"github":"https://github.com/igordive","tasks":[]},"nataliamotuz":{"github":"https://github.com/nataliamotuz","tasks":[]}}},"http://github.com/dzianisreznik":{"name":"dzianis reznik","github":"http://github.com/dzianisreznik/","students":{"eugene3112":{"github":"https://github.com/eugene3112","tasks":[]},"heat98":{"github":"https://github.com/heat98","tasks":["codejamcv\"","codejamcorejs\"","codejamdom,domevents\"","markup1","presentation"]},"tanyamatesha":{"github":"https://github.com/tanyamatesha","tasks":[]},"egorgorbik":{"github":"https://github.com/egorgorbik","tasks":["codejamcv\"","codejamcorejs\"","codejamdom,domevents\"","presentation"]},"vicrodzko":{"github":"https://github.com/vicrodzko","tasks":["codejamcv\"","codejamcorejs\"","codejamdom,domevents\"","markup1","presentation","youtube"]},"ilyatrat":{"github":"https://github.com/ilyatrat","tasks":["codejamdom,domevents\"","markup1","codejamcv\"","codejamcorejs\"","presentation"]},"unbelievablysmart":{"github":"https://github.com/unbelievablysmart","tasks":["codejamcorejs\"","codejamcv\"","markup1"]},"viktoryia-hrechykha":{"github":"https://github.com/viktoryia-hrechykha","tasks":[]}}},"xelsoid":{"name":"artsiom reutovich","github":"https://github.com/Xelsoid","students":{"ivanmatsur":{"github":"https://github.com/ivanmatsur","tasks":[]},"usermeme":{"github":"https://github.com/usermeme","tasks":["codejamcorejs\"","codejamcv\"","markup1","codejamdom,domevents\"","youtube","presentation","codejamscoreboard\""]},"virusss":{"github":"https://github.com/virusss","tasks":[]},"nikaz123":{"github":"https://github.com/nikaz123","tasks":["codejamcorejs\"","codejamcv\"","markup1","codejamdom,domevents\"","youtube","presentation"]}}},"razumovich":{"name":"aliaksandr razumovich","github":"https://github.com/razumovich/","students":{"kvatoferma":{"github":"https://github.com/kvatoferma","tasks":[]},"vladagaravaya":{"github":"https://github.com/vladagaravaya","tasks":[]},"chernyshovaalexandra":{"github":"https://github.com/chernyshovaalexandra","tasks":[]},"jacksonbr87":{"github":"https://github.com/jacksonbr87","tasks":[]}}},"dmitryromaniuk":{"name":"dzmitry ramaniuk","github":"https://github.com/DmitryRomaniuk","students":{"andreikrivets":{"github":"https://github.com/andreikrivets","tasks":[]},"lavazzakate":{"github":"https://github.com/lavazzakate","tasks":[]},"2kevink":{"github":"https://github.com/2kevink","tasks":["markup1","codejamcv\"","codejamdom,domevents\"","codejamcorejs\"","codejamcorejs\"","codejamscoreboard\"","youtube","youtube","presentation"]},"vladislavrebko":{"github":"https://github.com/vladislavrebko","tasks":[]},"amoyt":{"github":"https://github.com/amoyt","tasks":["markup1","codejamcorejs\"","codejamcv\"","markup1","codejamcorejs\"","codejamcorejs\""]}}},"yralko":{"name":"yauheni ralko","github":"https://github.com/yralko","students":{"anna-pronovich":{"github":"https://github.com/anna-pronovich","tasks":["codejamcv\"","codejamdom,domevents\"","markup1","markup1","presentation","codejamcorejs\""]},"artemiusv":{"github":"https://github.com/artemiusv","tasks":[]},"nataliakazakevich":{"github":"https://github.com/nataliakazakevich","tasks":[]},"kseniyasokolovskaya":{"github":"https://github.com/kseniyasokolovskaya","tasks":["codejamcv\"","codejamdom,domevents\"","markup1","codejamcorejs\""]},"zmichgen":{"github":"https://github.com/zmichgen","tasks":["codejamcv\"","codejamdom,domevents\"","markup1","presentation","codejamcorejs\""]}}},"anastasiaprivalova":{"name":"anastasiya pryvalava","github":"https://github.com/anastasiaprivalova","students":{"sergaunt":{"github":"https://github.com/sergaunt","tasks":["codejamcv\"","codejamcorejs\"","markup1","codejamdom,domevents\""]},"brateckrolikstudent":{"github":"https://github.com/brateckrolikstudent","tasks":["codejamcv\"","codejamcorejs\"","markup1","codejamdom,domevents\"","youtube","codejamscoreboard\"","presentation","presentation"]},"venomamd":{"github":"https://github.com/venomamd","tasks":[]},"vetal11":{"github":"https://github.com/vetal11","tasks":[]}}},"diprudnikov":{"name":"dzmitry prudnikau","github":"https://github.com/diprudnikov","students":{"leshka98":{"github":"https://github.com/leshka98","tasks":[]},"siarheikresik":{"github":"https://github.com/siarheikresik","tasks":["codejamcorejs\"","codejamcv\"","markup1","youtube","presentation"]},"dianakay":{"github":"https://github.com/dianakay","tasks":[]},"tvj888":{"github":"https://github.com/tvj888","tasks":[]},"alexkov90":{"github":"https://github.com/alexkov90","tasks":[]},"mpot7":{"github":"https://github.com/mpot7","tasks":["codejamcv\"","codejamcorejs\"","codejamdom,domevents\""]},"charmant":{"github":"https://github.com/charmant","tasks":[]}}},"anik188":{"name":"hanna pratasevich","github":"https://github.com/Anik188","students":{"horoshaya":{"github":"https://github.com/horoshaya","tasks":["codejamcv\"","codejamcorejs\"","rsactivist","markup1","codejamdom,domevents\"","rsactivist","presentation","youtube","codejamdom,domevents\"","codejamscoreboard\""]},"martinkevichyana":{"github":"https://github.com/martinkevichyana","tasks":[]},"montik-pc":{"github":"https://github.com/montik-pc","tasks":[]},"jeka98":{"github":"https://github.com/jeka98","tasks":["codejamcv\"","codejamcorejs\"","markup1","codejamdom,domevents\""]},"renardby":{"github":"https://github.com/renardby","tasks":["codejamcv\"","codejamcorejs\"","rsactivist","markup1","codejamdom,domevents\"","presentation","codejamscoreboard\"","presentation"]},"sergeyguchok":{"github":"https://github.com/sergeyguchok","tasks":["codejamcv\"","codejamcv\"","codejamcv\"","codejamcorejs\"","markup1","codejamdom,domevents\"","presentation","youtube","codejamscoreboard\""]},"aytsan":{"github":"https://github.com/aytsan","tasks":["codejamcorejs\"","codejamcv\"","markup1","codejamdom,domevents\""]}}},"lithiumfallen":{"name":"artsiom piakhota","github":"https://github.com/LithiumFallen","students":{"sunrisekovalevski":{"github":"https://github.com/sunrisekovalevski","tasks":["codejamcv\"","codejamcorejs\"","markup1","codejamdom,domevents\"","youtube","presentation"]},"spacebrains":{"github":"https://github.com/spacebrains","tasks":["codejamcv\"","codejamcorejs\"","markup1","codejamdom,domevents\""]},"pincherinka":{"github":"https://github.com/pincherinka","tasks":["codejamcv\"","codejamcorejs\""]},"victoriathebrave":{"github":"https://github.com/victoriathebrave","tasks":["codejamcv\"","codejamcorejs\"","codejamcorejs\"","markup1","codejamdom,domevents\"","youtube","presentation","codejamscoreboard\""]}}},"pasyukevich":{"name":"yauheni pasiukevich","github":"https://github.com/pasyukevich","students":{"yanachchchka":{"github":"https://github.com/yanachchchka","tasks":[]},"yalovikea":{"github":"https://github.com/yalovikea","tasks":[]},"volhashy":{"github":"https://github.com/volhashy","tasks":[]},"crunkagator":{"github":"https://github.com/crunkagator","tasks":["codejamcv\""]},"alenabde":{"github":"https://github.com/alenabde","tasks":["codejamcv\"","codejamcorejs\""]},"maksimyakush":{"github":"https://github.com/maksimyakush","tasks":["codejamcv\"","codejamcorejs\"","markup1","codejamdom,domevents\"","youtube","presentation"]},"boobaley":{"github":"https://github.com/boobaley","tasks":[]}}},"kirillpanov":{"name":"kiryl panou","github":"https://github.com/kirillpanov","students":{"helpthewalrus":{"github":"https://github.com/helpthewalrus","tasks":["codejamcv\"","codejamcorejs\""]},"aliaksandrlosich":{"github":"https://github.com/aliaksandrlosich","tasks":["codejamcv\"","codejamcorejs\"","markup1","codejamdom,domevents\"","presentation","codejamscoreboard\""]},"dmsolov":{"github":"https://github.com/dmsolov","tasks":[]},"bogdanka":{"github":"https://github.com/bogdanka","tasks":[]},"srjkaa":{"github":"https://github.com/srjkaa","tasks":[]},"godofnoobs":{"github":"https://github.com/godofnoobs","tasks":[]},"uivgray":{"github":"https://github.com/uivgray","tasks":["codejamcv\"","codejamcorejs\"","markup1","codejamdom,domevents\""]}}},"dzmitrypanamarenka":{"name":"dzmitry panamarenka","github":"https://github.com/dzmitrypanamarenka","students":{"stas4it":{"github":"https://github.com/stas4it","tasks":["codejamcorejs\"","codejamdom,domevents\""]},"vladislavmakarevich":{"github":"https://github.com/vladislavmakarevich","tasks":[]},"juliankov":{"github":"https://github.com/juliankov","tasks":["codejamcorejs\"","codejamdom,domevents\"","youtube","codejamscoreboard\"","presentation","markup1","codejamcv\""]},"niksrakevich":{"github":"https://github.com/niksrakevich","tasks":["codejamcorejs\"","codejamdom,domevents\"","presentation","youtube","codejamscoreboard\"","markup1","codejamcv\""]}}},"apalchys":{"name":"andrei palchys","github":"https://github.com/apalchys","students":{"vladyaremeko":{"github":"https://github.com/vladyaremeko","tasks":[]},"ton9q":{"github":"https://github.com/ton9q","tasks":["codejamcorejs\"","codejamcorejs\"","codejamdom,domevents\"","markup1","codejamcv\"","youtube","codejamscoreboard\""]},"nktvlkvch":{"github":"https://github.com/nktvlkvch","tasks":["codejamcv\"","codejamcorejs\"","markup1","codejamdom,domevents\""]},"valentinlipai":{"github":"https://github.com/valentinlipai","tasks":[]},"mazhoranta":{"github":"https://github.com/mazhoranta","tasks":[]}}},"olgapoddubko":{"name":"volha paddubka","github":"https://github.com/OlgaPoddubko","students":{"shet1990":{"github":"https://github.com/shet1990","tasks":[]},"maksagit":{"github":"https://github.com/maksagit","tasks":[]},"melk0sha":{"github":"https://github.com/melk0sha","tasks":[]},"tanyasamal":{"github":"https://github.com/tanyasamal","tasks":["codejamcv\"","markup1","codejamcorejs\"","codejamdom,domevents\"","codejamdom,domevents\"","youtube","presentation","codejamscoreboard\""]},"karsash":{"github":"https://github.com/karsash","tasks":[]},"dimadk24":{"github":"https://github.com/dimadk24","tasks":["codejamcv\"","codejamcorejs\"","markup1","codejamdom,domevents\"","youtube","presentation","codejamscoreboard\""]}}},"alexno":{"name":"aliaksandr novik","github":"https://github.com/AlexNo","students":{"xlopec23":{"github":"https://github.com/xlopec23","tasks":[]},"odinrossy":{"github":"https://github.com/odinrossy","tasks":[]},"vlad0mag0":{"github":"https://github.com/vlad0mag0","tasks":[]},"kir-22":{"github":"https://github.com/kir-22","tasks":["codejamcv\"","codejamcorejs\"","markup1","codejamdom,domevents\"","youtube"]},"snaiperlod":{"github":"https://github.com/snaiperlod","tasks":["codejamcv\"","codejamcorejs\""]},"llitrixkod":{"github":"https://github.com/llitrixkod","tasks":["codejamcv\"","codejamcorejs\"","markup1","codejamdom,domevents\"","youtube"]}}},"yananeronskaya":{"name":"yana niaronskaya","github":"https://github.com/YanaNeronskaya","students":{"ilyay95":{"github":"https://github.com/ilyay95","tasks":["codejamcorejs\"","codejamcv\"","markup1","codejamdom,domevents\"","youtube","presentation","codejamscoreboard\""]},"allexblaze":{"github":"https://github.com/allexblaze","tasks":[]},"dekim12":{"github":"https://github.com/dekim12","tasks":["codejamcorejs\"","codejamcv\"","markup1","codejamdom,domevents\"","youtube","presentation","rsactivist","codejamscoreboard\""]},"dimamavrin":{"github":"https://github.com/dimamavrin","tasks":[]},"vitalmizevich":{"github":"https://github.com/vitalmizevich","tasks":[]}}},"natashanekazakova":{"name":"natalya nekazakova","github":"https://github.com/natashanekazakova","students":{"wladimirmihalev":{"github":"https://github.com/wladimirmihalev","tasks":[]},"antoprokopovich":{"github":"https://github.com/antoprokopovich","tasks":[]},"iharpashkevich":{"github":"https://github.com/iharpashkevich","tasks":[]},"375291601334":{"github":"https://github.com/375291601334","tasks":["codejamcv\"","codejamcorejs\"","codejamdom,domevents\"","markup1","presentation","youtube"]}}},"mikhaillu":{"name":"mikhail naharayeu","github":"https://github.com/MikhailLU","students":{"elusiveway":{"github":"https://github.com/elusiveway","tasks":[]},"cirillius":{"github":"https://github.com/cirillius","tasks":[]},"eugenepochenkov":{"github":"https://github.com/eugenepochenkov","tasks":["markup1","codejamdom,domevents\""]},"lx-931203":{"github":"https://github.com/lx-931203","tasks":[]},"astravukh":{"github":"https://github.com/astravukh","tasks":[]},"zetorby":{"github":"https://github.com/zetorby","tasks":["markup1","codejamdom,domevents\""]}}},"maryia-n-n":{"name":"maryia nabzdorava","github":"https://github.com/Maryia-N-N","students":{"crypto-kittensseller":{"github":"https://github.com/crypto-kittensseller","tasks":["codejamcorejs\"","codejamcv\"","markup1","presentation"]},"dyadinmax":{"github":"https://github.com/dyadinmax","tasks":["codejamcv\"","codejamcorejs\""]},"alexeynovomlinets":{"github":"https://github.com/alexeynovomlinets","tasks":["codejamcv\"","codejamcorejs\"","markup1","presentation"]},"antonysawyer":{"github":"https://github.com/antonysawyer","tasks":["codejamcv\"","codejamcorejs\"","markup1","presentation"]}}},"mustafazadear":{"name":"arif mustafazade","github":"https://github.com/mustafazadeAR","students":{"sobolevyuri":{"github":"https://github.com/sobolevyuri","tasks":[]},"credov":{"github":"https://github.com/credov","tasks":["codejamcv\"","codejamcorejs\"","markup1"]},"clericus":{"github":"https://github.com/clericus","tasks":[]},"dbaceko":{"github":"https://github.com/dbaceko","tasks":["codejamcv\"","codejamcorejs\"","markup1","codejamdom,domevents\""]},"frontsideman":{"github":"https://github.com/frontsideman","tasks":["codejamcv\"","codejamcorejs\"","markup1","codejamdom,domevents\""]}}},"barysmarukhin":{"name":"barys marukhin","github":"https://github.com/barysmarukhin","students":{"denhock":{"github":"https://github.com/denhock","tasks":[]},"kirillgalimov":{"github":"https://github.com/kirillgalimov","tasks":["codejamcorejs\"","codejamcv\"","markup1","codejamdom,domevents\"","youtube","presentation","codejamscoreboard\""]},"igor-provotorov":{"github":"https://github.com/igor-provotorov","tasks":["codejamcv\"","codejamcorejs\"","markup1","codejamdom,domevents\"","codejamdom,domevents\"","youtube","youtube","presentation"]},"kamatozzzik":{"github":"https://github.com/kamatozzzik","tasks":["codejamcv\"","codejamcorejs\"","markup1","codejamdom,domevents\"","codejamdom,domevents\"","codejamdom,domevents\"","youtube"]}}},"themarkmarrone":{"name":"andrei markovich","github":"https://github.com/themarkmarrone","students":{"ener9ettt":{"github":"https://github.com/ener9ettt","tasks":[]},"petromath77":{"github":"https://github.com/petromath77","tasks":[]},"barsolet":{"github":"https://github.com/barsolet","tasks":[]},"yanrishbe":{"github":"https://github.com/yanrishbe","tasks":[]},"juliamv":{"github":"https://github.com/juliamv","tasks":["codejamcv\"","codejamcorejs\"","markup1","codejamdom,domevents\"","youtube","presentation","codejamscoreboard\""]},"icebergnevercries":{"github":"https://github.com/icebergnevercries","tasks":["codejamcv\"","codejamcorejs\"","markup1","codejamdom,domevents\""]},"tamarashautsova":{"github":"https://github.com/tamarashautsova","tasks":[]}}},"olgamardvilko":{"name":"volha mardvilka","github":"https://github.com/olgamardvilko","students":{"vladsanko":{"github":"https://github.com/vladsanko","tasks":[]},"serzhanhelena":{"github":"https://github.com/serzhanhelena","tasks":[]},"georgyminsk":{"github":"https://github.com/georgyminsk","tasks":["codejamcv\"","codejamcorejs\"","markup1","codejamdom,domevents\""]},"greg1996":{"github":"https://github.com/greg1996","tasks":["codejamcorejs\"","markup1"]},"goldenkit":{"github":"https://github.com/goldenkit","tasks":["codejamcv\"","codejamcorejs\"","markup1","codejamdom,domevents\""]}}},"aliaksandrmamonenka":{"name":"aliaksandr mamonenka","github":"https://github.com/AliaksandrMamonenka","students":{"moluram":{"github":"https://github.com/moluram","tasks":[]},"cheeska":{"github":"https://github.com/cheeska","tasks":[]},"nesteklo":{"github":"https://github.com/nesteklo","tasks":[]},"dasnein":{"github":"https://github.com/dasnein","tasks":["markup1","codejamcv\"","codejamcorejs\"","codejamdom,domevents\"","youtube","presentation","codejamscoreboard\""]}}},"muskos":{"name":"aliaksei makas","github":"https://github.com/Muskos","students":{"vireah":{"github":"https://github.com/vireah","tasks":["codejamcv\"","codejamcorejs\"","markup1"]},"yarobei":{"github":"https://github.com/yarobei","tasks":[]},"alexandrtichon":{"github":"https://github.com/alexandrtichon","tasks":["codejamcv\"","codejamcorejs\"","markup1","codejamdom,domevents\"","codejamscoreboard\"","youtube"]},"yanyan155":{"github":"https://github.com/yanyan155","tasks":["codejamcv\"","codejamcorejs\"","markup1","codejamdom,domevents\""]},"pkutsilina":{"github":"https://github.com/pkutsilina","tasks":["codejamcorejs\""]}}},"lykovartem":{"name":"artsiom lykau","github":"https://github.com/lykovartem","students":{"glebhleb":{"github":"https://github.com/glebhleb","tasks":[]},"segrey1989":{"github":"https://github.com/segrey1989","tasks":["codejamcv\"","codejamcorejs\"","markup1","codejamdom,domevents\"","youtube","presentation"]},"kotukjubotuk":{"github":"https://github.com/kotukjubotuk","tasks":[]},"nikkola07":{"github":"https://github.com/nikkola07","tasks":[]},"alexandershaternik":{"github":"https://github.com/alexandershaternik","tasks":[]},"okband":{"github":"https://github.com/okband","tasks":[]}}},"lipskiy-aleh":{"name":"aleh lipski","github":"https://github.com/lipskiy-aleh","students":{"agentumbrella":{"github":"https://github.com/agentumbrella","tasks":["codejamcv\"","codejamcorejs\"","markup1","codejamdom,domevents\"","presentation"]},"justforwebcoding":{"github":"https://github.com/justforwebcoding","tasks":[]},"anastasiaburlo":{"github":"https://github.com/anastasiaburlo","tasks":[]},"devandscorp":{"github":"https://github.com/devandscorp","tasks":["codejamcv\"","codejamcorejs\"","markup1","codejamdom,domevents\"","presentation"]},"qucca":{"github":"https://github.com/qucca","tasks":[]},"lexbogos":{"github":"https://github.com/lexbogos","tasks":["codejamcv\"","codejamcorejs\"","codejamdom,domevents\"","presentation"]},"zebabrat":{"github":"https://github.com/zebabrat","tasks":[]}}},"liaukou":{"name":"andrei liaukou","github":"https://github.com/liaukou","students":{"dimasquared":{"github":"https://github.com/dimasquared","tasks":["codejamcv\"","codejamcorejs\""]},"smetaninpavel":{"github":"https://github.com/smetaninpavel","tasks":[]},"ol4ash":{"github":"https://github.com/ol4ash","tasks":["codejamcv\"","codejamcorejs\"","markup1","codejamdom,domevents\""]},"kasper1999":{"github":"https://github.com/kasper1999","tasks":["codejamcv\"","codejamcorejs\"","markup1","codejamdom,domevents\""]},"ivanmikhailenka1":{"github":"https://github.com/ivanmikhailenka1","tasks":[]}}},"lenkouandrei":{"name":"andrei lenkou","github":"https://github.com/LenkouAndrei","students":{"goner52":{"github":"https://github.com/goner52","tasks":["markup1","codejamdom,domevents\""]},"poyuki":{"github":"https://github.com/poyuki","tasks":["codejamcv\"","codejamcorejs\"","markup1","youtube"]},"elmavis":{"github":"https://github.com/elmavis","tasks":[]},"rafchillons":{"github":"https://github.com/rafchillons","tasks":["codejamcv\"","codejamcorejs\""]},"kirylalexandrovich":{"github":"https://github.com/kirylalexandrovich","tasks":["codejamcv\"","codejamcorejs\"","markup1","codejamdom,domevents\"","youtube","presentation"]},"vlad9719":{"github":"https://github.com/vlad9719","tasks":[]},"mg3442":{"github":"https://github.com/mg3442","tasks":[]}}},"lavitr":{"name":"ron lavit","github":"https://github.com/Lavitr","students":{"mrdemonrush":{"github":"https://github.com/mrdemonrush","tasks":["codejamcv\"","codejamcorejs\"","codejamdom,domevents\"","markup1"]},"h0qw010xz":{"github":"https://github.com/h0qw010xz","tasks":[]},"nikitaklepanosov":{"github":"https://github.com/nikitaklepanosov","tasks":["codejamcv\"","codejamcorejs\"","codejamdom,domevents\"","codejamdom,domevents\"","codejamdom,domevents\"","markup1"]},"provedenceva":{"github":"https://github.com/provedenceva","tasks":["codejamcv\"","codejamcorejs\"","codejamdom,domevents\"","markup1"]},"daryz":{"github":"https://github.com/daryz","tasks":[]}}},"artemlatyshev":{"name":"artsiom latyshau","github":"https://github.com/artemlatyshev","students":{"sergeiobolevich":{"github":"https://github.com/sergeiobolevich","tasks":["codejamcv\"","codejamcorejs\"","codejamdom,domevents\""]},"dimashcherbakov":{"github":"https://github.com/dimashcherbakov","tasks":[]},"feulia":{"github":"https://github.com/feulia","tasks":[]},"magi-a":{"github":"https://github.com/magi-a","tasks":["codejamcv\"","codejamcorejs\"","codejamdom,domevents\"","youtube","presentation"]},"andrewyanushkevich":{"github":"https://github.com/andrewyanushkevich","tasks":["codejamcv\"","codejamcorejs\"","codejamdom,domevents\""]}}},"viachaslau-latushkin":{"name":"viachaslau latushkin","github":"https://github.com/viachaslau-latushkin","students":{"alexandrasitnikova":{"github":"https://github.com/alexandrasitnikova","tasks":["codejamcv\"","codejamcorejs\"","codejamdom,domevents\"","markup1","markup1"]},"vitalibrych333":{"github":"https://github.com/vitalibrych333","tasks":["codejamcv\"","codejamcorejs\"","codejamdom,domevents\"","markup1","presentation","youtube","codejamscoreboard\""]},"pavelkiru":{"github":"https://github.com/pavelkiru","tasks":[]},"shestakoff1441":{"github":"https://github.com/shestakoff1441","tasks":[]},"katezhukel":{"github":"https://github.com/katezhukel","tasks":[]}}},"aliaksandrkuzniatsou":{"name":"aliaksandr kuzniatsou","github":"https://github.com/AliaksandrKuzniatsou","students":{"apivovarchik":{"github":"https://github.com/apivovarchik","tasks":["markup1","codejamdom,domevents\""]},"ruslandimitriuk":{"github":"https://github.com/ruslandimitriuk","tasks":[]},"temachkin11":{"github":"https://github.com/temachkin11","tasks":[]},"iamhappy2day":{"github":"https://github.com/iamhappy2day","tasks":[]},"katiekruchko":{"github":"https://github.com/katiekruchko","tasks":[]},"artser97":{"github":"https://github.com/artser97","tasks":[]},"stasnegreev":{"github":"https://github.com/stasnegreev","tasks":[]}}},"pavelkuzniatsou":{"name":"pavel kuzniatsou","github":"https://github.com/PavelKuzniatsou","students":{"maxbrainygame":{"github":"https://github.com/maxbrainygame","tasks":[]},"oliver337":{"github":"https://github.com/oliver337","tasks":[]},"kotiknalune42":{"github":"https://github.com/kotiknalune42","tasks":[]},"akselatom":{"github":"https://github.com/akselatom","tasks":[]},"maryiasiamenava":{"github":"https://github.com/maryiasiamenava","tasks":[]},"kotcher1":{"github":"https://github.com/kotcher1","tasks":["codejamcorejs\"","markup1","codejamdom,domevents\""]},"kirilltovpinets":{"github":"https://github.com/kirilltovpinets","tasks":["codejamcv\"","codejamcorejs\"","markup1","codejamdom,domevents\"","youtube","presentation","codejamscoreboard\""]}}},"agentkb":{"name":"bahdan kutas","github":"https://github.com/AgentKB","students":{"litwin90":{"github":"https://github.com/litwin90","tasks":[]},"dzmitrybabak":{"github":"https://github.com/dzmitrybabak","tasks":["codejamcv\"","codejamcorejs\"","markup1","codejamdom,domevents\""]},"systemghost":{"github":"https://github.com/systemghost","tasks":["codejamcv\"","codejamcorejs\"","markup1","codejamdom,domevents\"","youtube","presentation","codejamscoreboard\""]},"eugenetime":{"github":"https://github.com/eugenetime","tasks":["codejamcv\"","codejamcorejs\""]},"alexnaidovich":{"github":"https://github.com/alexnaidovich","tasks":[]},"ivanchikovvalentin":{"github":"https://github.com/ivanchikovvalentin","tasks":["codejamcv\"","codejamcorejs\"","markup1","codejamdom,domevents\""]},"ewelai":{"github":"https://github.com/ewelai","tasks":["codejamcv\"","codejamcorejs\"","markup1","codejamdom,domevents\""]}}},"woozzone":{"name":"viktar kurbatski","github":"https://github.com/Woozzone","students":{"bardashevich-matvei":{"github":"https://github.com/bardashevich-matvei","tasks":["codejamcv\"","codejamcorejs\"","markup1","codejamdom,domevents\"","youtube"]},"korbann":{"github":"https://github.com/korbann","tasks":[]},"yevgeniypy":{"github":"https://github.com/yevgeniypy","tasks":["codejamcv\"","codejamcorejs\"","codejamdom,domevents\"","markup1","presentation"]},"tatyana-andreichyk":{"github":"https://github.com/tatyana-andreichyk","tasks":["codejamcv\"","codejamcorejs\"","markup1","codejamdom,domevents\"","youtube","codejamscoreboard\""]},"supersmf":{"github":"https://github.com/supersmf","tasks":[]}}},"kukolcaalexandra":{"name":"alexandra kukolca","github":"https://github.com/KukolcaAlexandra","students":{"sxe2255":{"github":"https://github.com/sxe2255","tasks":[]},"vovair":{"github":"https://github.com/vovair","tasks":[]},"ingvaroldd":{"github":"https://github.com/ingvaroldd","tasks":["codejamcorejs\"","codejamcv\""]},"bragodin":{"github":"https://github.com/bragodin","tasks":["markup1","codejamdom,domevents\""]},"fantom141":{"github":"https://github.com/fantom141","tasks":["codejamcorejs\"","codejamcv\""]},"samo-war":{"github":"https://github.com/samo-war","tasks":["codejamcorejs\"","codejamcv\"","markup1","codejamdom,domevents\"","youtube","presentation"]}}},"xeontem":{"name":"artsiom kukharev","github":"https://github.com/xeontem","students":{"silichstudent":{"github":"https://github.com/silichstudent","tasks":[]},"vvikota":{"github":"https://github.com/vvikota","tasks":["codejamcv\"","codejamcorejs\"","codejamdom,domevents\"","presentation","markup1","youtube"]},"leonard1k":{"github":"https://github.com/leonard1k","tasks":[]},"mariakisel":{"github":"https://github.com/mariakisel","tasks":["codejamcv\"","codejamcorejs\"","markup1","codejamdom,domevents\"","presentation","markup1"]},"qxfisher":{"github":"https://github.com/qxfisher","tasks":["codejamcv\"","codejamcorejs\"","markup1","codejamdom,domevents\"","youtube","presentation"]},"bulbazubr":{"github":"https://github.com/bulbazubr","tasks":[]}}},"linus2228":{"name":"dzmitry kudla","github":"https://github.com/Linus2228","students":{"sergeybaranovichi":{"github":"https://github.com/sergeybaranovichi","tasks":["codejamcv\"","codejamcorejs\"","markup1","codejamdom,domevents\""]},"karina198":{"github":"https://github.com/karina198","tasks":[]},"arturkudlo":{"github":"https://github.com/arturkudlo","tasks":["codejamcv\"","codejamcorejs\"","markup1","codejamdom,domevents\"","youtube","codejamscoreboard\"","presentation"]},"dimasofff":{"github":"https://github.com/dimasofff","tasks":["codejamcv\"","codejamcorejs\"","markup1","codejamdom,domevents\""]},"6alex6kash6":{"github":"https://github.com/6alex6kash6","tasks":[]}}},"shank111":{"name":"denis kravchenko","github":"https://github.com/Shank111","students":{"kirillfilipp":{"github":"https://github.com/kirillfilipp","tasks":["codejamcv\"","codejamcorejs\"","markup1","codejamdom,domevents\""]},"gemsgame":{"github":"https://github.com/gemsgame","tasks":["markup1","codejamdom,domevents\"","codejamcorejs\"","codejamcv\"","codejamcv\""]},"axissixa57":{"github":"https://github.com/axissixa57","tasks":[]},"maxstarovoitov":{"github":"https://github.com/maxstarovoitov","tasks":[]},"nemkev":{"github":"https://github.com/nemkev","tasks":["codejamcv\"","codejamcorejs\"","markup1","codejamdom,domevents\"","codejamscoreboard\"","presentation"]}}},"aliakseikrauchanka":{"name":"aliaksei krauchanka","github":"https://github.com/aliakseikrauchanka","students":{"latiertiw":{"github":"https://github.com/latiertiw","tasks":["codejamcv\"","codejamcorejs\"","markup1","codejamdom,domevents\"","youtube","codejamscoreboard\""]},"sined1":{"github":"https://github.com/sined1","tasks":[]},"vladzuev":{"github":"https://github.com/vladzuev","tasks":[]},"christinaalimova":{"github":"https://github.com/christinaalimova","tasks":[]}}},"error404as":{"name":"vitali krasnou","github":"https://github.com/error404as/","students":{"robertiqk":{"github":"https://github.com/robertiqk","tasks":["codejamcv\"","codejamcorejs\""]},"pozharitskiy":{"github":"https://github.com/pozharitskiy","tasks":["codejamcv\"","codejamcorejs\"","markup1","youtube","presentation"]},"aliakseik19":{"github":"https://github.com/aliakseik19","tasks":[]},"tarsupon":{"github":"https://github.com/tarsupon","tasks":["codejamcv\"","codejamcorejs\"","markup1","codejamdom,domevents\"","youtube","presentation"]}}},"aliaksandrkrasnou":{"name":"aliaksandr krasnou","github":"https://github.com/aliaksandrkrasnou","students":{"andrey-lobach":{"github":"https://github.com/andrey-lobach","tasks":["codejamcorejs\"","markup1","codejamcorejs\"","codejamdom,domevents\"","codejamcv\""]},"pitergtx":{"github":"https://github.com/pitergtx","tasks":[]},"alexandravlasenko":{"github":"https://github.com/alexandravlasenko","tasks":["markup1","codejamdom,domevents\""]},"painincoming":{"github":"https://github.com/painincoming","tasks":["codejamcorejs\"","codejamcorejs\"","markup1","codejamdom,domevents\"","codejamcv\""]}}},"vladislavkovaliov":{"name":"vladislav kovaliov","github":"https://github.com/vladislavkovaliov/","students":{"roman-nareiko":{"github":"https://github.com/roman-nareiko","tasks":[]},"evilamany":{"github":"https://github.com/evilamany","tasks":[]},"xvorob":{"github":"https://github.com/xvorob","tasks":[]},"pelya98":{"github":"https://github.com/pelya98","tasks":[]}}},"korotkin":{"name":"sergeh korotkin","github":"https://github.com/korotkin","students":{"pavelsab":{"github":"https://github.com/pavelsab","tasks":[]},"ihartsykaka":{"github":"https://github.com/ihartsykaka","tasks":[]},"vldshch":{"github":"https://github.com/vldshch","tasks":[]},"naijelo":{"github":"https://github.com/naijelo","tasks":[]},"tridenet":{"github":"https://github.com/tridenet","tasks":[]},"darinalitvin":{"github":"https://github.com/darinalitvin","tasks":[]},"zhechka":{"github":"https://github.com/zhechka","tasks":[]}}},"papialoushka":{"name":"alena korachkina","github":"https://github.com/Papialoushka","students":{"dmitryduk3":{"github":"https://github.com/dmitryduk3","tasks":[]},"nikola2390":{"github":"https://github.com/nikola2390","tasks":[]},"sashajohnson":{"github":"https://github.com/sashajohnson","tasks":[]},"yagorka1":{"github":"https://github.com/yagorka1","tasks":[]}}},"candentira":{"name":"viktoryia klimenka","github":"https://github.com/candentira","students":{"palessie":{"github":"https://github.com/palessie","tasks":[]},"ustilushka":{"github":"https://github.com/ustilushka","tasks":[]},"zzvipz":{"github":"https://github.com/zzvipz","tasks":["codejamcv\"","codejamcorejs\"","codejamcorejs\"","markup1","codejamdom,domevents\"","presentation"]},"dmitrylenko":{"github":"https://github.com/dmitrylenko","tasks":["codejamcv\"","codejamcorejs\"","codejamcorejs\"","markup1","codejamdom,domevents\"","presentation","codejamscoreboard\""]},"underdoglzd":{"github":"https://github.com/underdoglzd","tasks":["codejamcv\"","codejamcorejs\"","codejamcorejs\"","markup1","codejamdom,domevents\""]}}},"sleepwalky":{"name":"aliaksandr kleshchukevich","github":"https://github.com/sleepwalky","students":{"noviceblunderer":{"github":"https://github.com/noviceblunderer","tasks":["codejamcv\"","codejamcorejs\"","codejamdom,domevents\""]},"kristalys":{"github":"https://github.com/kristalys","tasks":[]},"splin-shady":{"github":"https://github.com/splin-shady","tasks":[]},"katrin-kot":{"github":"https://github.com/katrin-kot","tasks":["codejamcv\"","codejamcorejs\"","codejamdom,domevents\"","presentation"]},"gattygamaun":{"github":"https://github.com/gattygamaun","tasks":["codejamcv\"","codejamcorejs\"","presentation","codejamdom,domevents\""]},"mariyapolt":{"github":"https://github.com/mariyapolt","tasks":["codejamcv\"","codejamcorejs\"","presentation","codejamdom,domevents\""]}}},"fallenby1":{"name":"aliaksei khlebnikau","github":"https://github.com/FallenBY1","students":{"katepavlovich":{"github":"https://github.com/katepavlovich","tasks":["codejamcv\"","codejamcorejs\"","markup1","codejamdom,domevents\"","youtube"]},"youngbrick":{"github":"https://github.com/youngbrick","tasks":["codejamcv\"","codejamcorejs\"","markup1","codejamdom,domevents\"","youtube"]},"alekengineer":{"github":"https://github.com/alekengineer","tasks":["codejamcv\"","codejamcorejs\""]},"kottt4":{"github":"https://github.com/kottt4","tasks":["codejamcv\"","codejamcorejs\"","markup1","codejamdom,domevents\""]},"walkunderrain":{"github":"https://github.com/walkunderrain","tasks":[]}}},"arturminsksum":{"name":"artur kazlouski","github":"https://github.com/arturminsksum","students":{"a-lika":{"github":"https://github.com/a-lika","tasks":[]},"uniqkue":{"github":"https://github.com/uniqkue","tasks":[]},"sqwezzy":{"github":"https://github.com/sqwezzy","tasks":[]},"nikaneider":{"github":"https://github.com/nikaneider","tasks":[]},"rebellix":{"github":"https://github.com/rebellix","tasks":["codejamcv\"","codejamcorejs\"","markup1","codejamdom,domevents\"","youtube","presentation"]}}},"shparkivozhyk":{"name":"maryna kavetskaya","github":"https://github.com/shparkivozhyk","students":{"sburnt":{"github":"https://github.com/sburnt","tasks":["codejamcorejs\"","codejamcv\"","markup1","codejamdom,domevents\""]},"tserekhivan":{"github":"https://github.com/tserekhivan","tasks":["codejamcorejs\"","codejamcv\"","codejamcv\"","markup1","codejamdom,domevents\"","youtube","codejamscoreboard\"","presentation"]},"presidentsboyfriend":{"github":"https://github.com/presidentsboyfriend","tasks":["codejamcorejs\"","codejamcv\"","markup1"]},"eugenekhristo":{"github":"https://github.com/eugenekhristo","tasks":[]}}},"nikkov17":{"name":"mikalai kavaliou","github":"https://github.com/Nikkov17","students":{"artichoks":{"github":"https://github.com/artichoks","tasks":[]},"anastasiyanovikovag":{"github":"https://github.com/anastasiyanovikovag","tasks":["codejamcv\"","codejamcorejs\"","markup1","codejamdom,domevents\""]},"margaretmint":{"github":"https://github.com/margaretmint","tasks":["codejamcv\"","codejamcorejs\"","markup1","codejamdom,domevents\""]},"anastasiyamazura":{"github":"https://github.com/anastasiyamazura","tasks":["codejamcv\"","codejamcorejs\"","markup1","codejamdom,domevents\"","youtube","youtube","presentation","codejamscoreboard\""]},"dezman66":{"github":"https://github.com/dezman66","tasks":[]},"exedystyle":{"github":"https://github.com/exedystyle","tasks":["codejamcv\"","codejamcorejs\"","markup1","codejamdom,domevents\"","youtube"]},"gaddyya":{"github":"https://github.com/gaddyya","tasks":["codejamcv\"","codejamcorejs\"","markup1","codejamdom,domevents\"","youtube","youtube","presentation","codejamscoreboard\""]}}},"yanaselin":{"name":"yana karotkina","github":"https://github.com/yanaSelin","students":{"bsiropchik":{"github":"https://github.com/bsiropchik","tasks":["codejamcv\"","codejamcorejs\"","markup1","codejamdom,domevents\"","youtube","presentation","codejamscoreboard\""]},"scratchor":{"github":"https://github.com/scratchor","tasks":["codejamcv\"","codejamcorejs\"","markup1","codejamdom,domevents\"","youtube","youtube"]},"montes5":{"github":"https://github.com/montes5","tasks":["codejamcv\"","codejamcorejs\""]},"mrspunki":{"github":"https://github.com/mrspunki","tasks":["codejamcv\"","codejamcorejs\"","markup1","markup1","codejamdom,domevents\""]},"maksstef":{"github":"https://github.com/maksstef","tasks":[]}}},"katekaranets":{"name":"katsiaryna karanets","github":"https://github.com/katekaranets","students":{"kozelkoff":{"github":"https://github.com/kozelkoff","tasks":["codejamcv\""]},"vladislavshyian":{"github":"https://github.com/vladislavshyian","tasks":[]},"gleb-kukobnikov":{"github":"https://github.com/gleb-kukobnikov","tasks":[]},"sokol147":{"github":"https://github.com/sokol147","tasks":["codejamcv\"","codejamcorejs\"","markup1","codejamdom,domevents\"","presentation"]},"dantewitcher":{"github":"https://github.com/dantewitcher","tasks":[]},"natiedei":{"github":"https://github.com/natiedei","tasks":["codejamcv\""]},"aliaksandrarybak":{"github":"https://github.com/aliaksandrarybak","tasks":["codejamcv\"","codejamcorejs\"","markup1","codejamdom,domevents\"","presentation"]}}},"ivashkovaliza":{"name":"elizaveta ivashkova","github":"https://github.com/ivashkovaliza","students":{"stationtostation":{"github":"https://github.com/stationtostation","tasks":["codejamcorejs\"","codejamcv\"","markup1","codejamcorejs\"","codejamdom,domevents\"","presentation"]},"tatsianacs":{"github":"https://github.com/tatsianacs","tasks":["codejamcorejs\"","codejamcv\"","markup1","codejamdom,domevents\"","youtube","rsactivist","presentation","rsactivist","codejamscoreboard\""]},"kharuk":{"github":"https://github.com/kharuk","tasks":["codejamcorejs\"","codejamcv\"","markup1","codejamdom,domevents\"","youtube","presentation","codejamscoreboard\""]},"wald3":{"github":"https://github.com/wald3","tasks":[]}}},"helenegritsuk":{"name":"alena hrytsuk","github":"https://github.com/HeleneGritsuk","students":{"devildummy":{"github":"https://github.com/devildummy","tasks":["codejamcv\"","codejamcorejs\"","markup1","presentation","presentation","codejamdom,domevents\"","codejamscoreboard\""]},"dzmitry-karachun-1987":{"github":"https://github.com/dzmitry-karachun-1987","tasks":["codejamcv\"","codejamcorejs\"","markup1"]},"serg8":{"github":"https://github.com/serg8","tasks":["codejamcv\"","codejamcorejs\"","markup1","presentation","presentation","codejamdom,domevents\"","codejamscoreboard\""]},"nik-av":{"github":"https://github.com/nik-av","tasks":[]},"kishkun":{"github":"https://github.com/kishkun","tasks":[]},"tsygancova":{"github":"https://github.com/tsygancova","tasks":[]}}},"falizyer":{"name":"dzmitry hrachou","github":"https://github.com/falizyer","students":{"bespodobno":{"github":"https://github.com/bespodobno","tasks":[]},"anastasia1627":{"github":"https://github.com/anastasia1627","tasks":[]},"basch1727":{"github":"https://github.com/basch1727","tasks":["codejamdom,domevents\"","markup1"]},"lizabredberry":{"github":"https://github.com/lizabredberry","tasks":[]},"zartaich":{"github":"https://github.com/zartaich","tasks":[]},"estel1591":{"github":"https://github.com/estel1591","tasks":["markup1","codejamdom,domevents\"","codejamcv\"","codejamcorejs\"","presentation","codejamscoreboard\""]},"alekseymishuk":{"github":"https://github.com/alekseymishuk","tasks":[]}}},"annagrebenyuk":{"name":"hanna hrabianiuk","github":"https://github.com/AnnaGrebenyuk","students":{"yuliyahlukhatarenka":{"github":"https://github.com/yuliyahlukhatarenka","tasks":["codejamcv\"","codejamcorejs\"","markup1","codejamdom,domevents\"","codejamscoreboard\"","presentation"]},"lapa17":{"github":"https://github.com/lapa17","tasks":[]},"dmitrylutskovich":{"github":"https://github.com/dmitrylutskovich","tasks":["codejamcv\"","codejamcorejs\"","markup1","codejamdom,domevents\""]},"vladst90":{"github":"https://github.com/vladst90","tasks":[]},"atryomparfenenkov":{"github":"https://github.com/atryomparfenenkov","tasks":[]}}},"evgladkiy":{"name":"yauheni hladki","github":"https://github.com/evgladkiy","students":{"evgenijkorob":{"github":"https://github.com/evgenijkorob","tasks":["codejamcv\"","codejamcorejs\"","codejamdom,domevents\"","markup1"]},"anxair":{"github":"https://github.com/anxair","tasks":[]},"siarohin":{"github":"https://github.com/siarohin","tasks":["codejamcv\"","codejamcorejs\"","markup1","codejamdom,domevents\"","youtube","presentation","codejamscoreboard\""]},"svyatlo":{"github":"https://github.com/svyatlo","tasks":["codejamcorejs\"","codejamcv\"","markup1","codejamdom,domevents\"","youtube","youtube","presentation","codejamscoreboard\""]},"shurpelevas":{"github":"https://github.com/shurpelevas","tasks":[]}}},"evgeniigrh":{"name":"yauheni harokh","github":"https://github.com/EvgeniiGrh","students":{"antonprotas":{"github":"https://github.com/antonprotas","tasks":["codejamcv\"","codejamcorejs\"","markup1","codejamdom,domevents\""]},"mickbetch":{"github":"https://github.com/mickbetch","tasks":[]},"oconely":{"github":"https://github.com/oconely","tasks":["codejamcv\""]},"natalianekrashevich":{"github":"https://github.com/natalianekrashevich","tasks":[]},"iryna-mazura":{"github":"https://github.com/iryna-mazura","tasks":["codejamcv\"","codejamcorejs\"","codejamcorejs\"","markup1","codejamdom,domevents\"","youtube","rsactivist","presentation","codejamscoreboard\""]},"kamenkoalexandr":{"github":"https://github.com/kamenkoalexandr","tasks":[]},"garin87":{"github":"https://github.com/garin87","tasks":[]}}},"amsterget":{"name":"ilya hancharyk","github":"https://github.com/AmsterGet","students":{"tebeskashi":{"github":"https://github.com/tebeskashi","tasks":["codejamcorejs\"","markup1","presentation","codejamdom,domevents\"","youtube"]},"pinkrefugee":{"github":"https://github.com/pinkrefugee","tasks":["codejamcv\"","codejamcorejs\"","markup1","presentation","codejamdom,domevents\"","codejamscoreboard\"","youtube"]},"daqueze21":{"github":"https://github.com/daqueze21","tasks":[]},"beetle23":{"github":"https://github.com/beetle23","tasks":[]},"lynyx":{"github":"https://github.com/lynyx","tasks":[]},"tomsssm":{"github":"https://github.com/tomsssm","tasks":["codejamcorejs\"","markup1"]},"colambus13":{"github":"https://github.com/colambus13","tasks":["codejamcv\"","codejamcorejs\"","markup1"]}}},"yuliahope":{"name":"yuliya haluza","github":"https://github.com/yuliaHope","students":{"artyommakarov":{"github":"https://github.com/artyommakarov","tasks":[]},"levsha87":{"github":"https://github.com/levsha87","tasks":[]},"hottab9595":{"github":"https://github.com/hottab9595","tasks":[]},"achyrych":{"github":"https://github.com/achyrych","tasks":[]},"arkadz":{"github":"https://github.com/arkadz","tasks":[]},"maniuska":{"github":"https://github.com/maniuska","tasks":[]},"sachoks":{"github":"https://github.com/sachoks","tasks":[]}}},"predokmif":{"name":"konstantin grigorchuk","github":"https://github.com/PredokMiF","students":{"belkacraft":{"github":"https://github.com/belkacraft","tasks":["codejamcv\"","codejamcorejs\"","markup1","codejamdom,domevents\""]},"kasatka660":{"github":"https://github.com/kasatka660","tasks":["codejamcv\"","codejamcorejs\"","markup1","codejamdom,domevents\"","youtube","presentation","codejamscoreboard\""]},"warryr":{"github":"https://github.com/warryr","tasks":["codejamcv\"","codejamcorejs\"","markup1","codejamdom,domevents\"","youtube","presentation","codejamscoreboard\""]},"alexandrapozniak":{"github":"https://github.com/alexandrapozniak","tasks":[]},"yuliabakhar":{"github":"https://github.com/yuliabakhar","tasks":[]}}},"valeragorobets":{"name":"valeri gorobets","github":"https://github.com/valeraGorobets/","students":{"ivandubrouski":{"github":"https://github.com/ivandubrouski","tasks":["codejamcorejs\"","codejamcv\""]},"mrforsyte":{"github":"https://github.com/mrforsyte","tasks":[]},"krisstets":{"github":"https://github.com/krisstets","tasks":[]},"yuriy17":{"github":"https://github.com/yuriy17","tasks":[]},"olgakuksa":{"github":"https://github.com/olgakuksa","tasks":["codejamcorejs\"","markup1","codejamdom,domevents\"","codejamscoreboard\"","presentation"]},"eliznovo":{"github":"https://github.com/eliznovo","tasks":[]},"vitalij21":{"github":"https://github.com/vitalij21","tasks":[]}}},"pavelglebov":{"name":"pavel glebov","github":"https://github.com/pavelglebov","students":{"oaliona":{"github":"https://github.com/oaliona","tasks":["codejamcv\"","codejamcorejs\""]},"feodorius":{"github":"https://github.com/feodorius","tasks":["codejamcv\"","codejamcorejs\""]},"ihar777":{"github":"https://github.com/ihar777","tasks":["codejamcv\"","codejamcorejs\"","markup1"]},"dzianiskavalionak":{"github":"https://github.com/dzianiskavalionak","tasks":["codejamcv\"","codejamcorejs\"","markup1","codejamdom,domevents\""]},"alexsmyk1992":{"github":"https://github.com/alexsmyk1992","tasks":[]},"vbkoshak":{"github":"https://github.com/vbkoshak","tasks":["codejamcv\"","codejamcorejs\"","markup1","codejamdom,domevents\""]}}},"aliaksandrfiodarau":{"name":"aliaksandr fiodarau","github":"https://github.com/aliaksandrfiodarau","students":{"burach0k":{"github":"https://github.com/burach0k","tasks":["codejamcv\"","codejamcorejs\"","markup1","codejamdom,domevents\"","youtube"]},"denyingthetruth":{"github":"https://github.com/denyingthetruth","tasks":["codejamcv\"","codejamcorejs\"","markup1","codejamdom,domevents\""]},"invikto":{"github":"https://github.com/invikto","tasks":[]},"khaliulinroman":{"github":"https://github.com/khaliulinroman","tasks":["codejamcv\"","codejamcorejs\"","markup1","codejamdom,domevents\""]}}},"denisdashkevich":{"name":"dzianis dashkevich","github":"https://github.com/DenisDashkevich","students":{"yevganytyurin":{"github":"https://github.com/yevganytyurin","tasks":[]},"pofs":{"github":"https://github.com/pofs","tasks":[]},"alexeykuril0":{"github":"https://github.com/alexeykuril0","tasks":["codejamcorejs\"","markup1","codejamdom,domevents\"","youtube","presentation"]},"kragov":{"github":"https://github.com/kragov","tasks":[]},"gruzinskiiartem":{"github":"https://github.com/gruzinskiiartem","tasks":[]},"pivchenkosv":{"github":"https://github.com/pivchenkosv","tasks":[]},"andreisavelyev":{"github":"https://github.com/andreisavelyev","tasks":["codejamcv\"","codejamcorejs\"","markup1","codejamdom,domevents\"","youtube","codejamscoreboard\"","presentation"]}}},"sergey-churilin":{"name":"siarhei churylin","github":"https://github.com/Sergey-Churilin","students":{"gegorov":{"github":"https://github.com/gegorov","tasks":["codejamcv\"","codejamcorejs\"","markup1","codejamdom,domevents\"","rsactivist"]},"ilyakabanov":{"github":"https://github.com/ilyakabanov","tasks":[]},"yurec0gurec":{"github":"https://github.com/yurec0gurec","tasks":["codejamcv\"","codejamcorejs\"","markup1","codejamdom,domevents\"","youtube","markup1","markup1","codejamscoreboard\"","presentation"]},"gubnich":{"github":"https://github.com/gubnich","tasks":["codejamcv\"","codejamcorejs\"","markup1","codejamdom,domevents\"","youtube","codejamscoreboard\"","presentation"]}}},"dzmitry-chuchva":{"name":"dzmitry chuchva","github":"https://github.com/dzmitry-chuchva","students":{"modrix":{"github":"https://github.com/modrix","tasks":[]},"scarletcamomile":{"github":"https://github.com/scarletcamomile","tasks":["codejamcorejs\"","codejamcv\"","markup1","codejamdom,domevents\""]},"tani4ik":{"github":"https://github.com/tani4ik","tasks":["codejamcorejs\"","codejamcv\"","markup1","codejamdom,domevents\""]}}},"eugenech":{"name":"yauhen chaika","github":"https://github.com/EugeneCh","students":{"ivchenkopavel":{"github":"https://github.com/ivchenkopavel","tasks":["codejamcv\"","codejamcorejs\""]},"ruboscope":{"github":"https://github.com/ruboscope","tasks":["codejamcv\"","codejamcorejs\"","codejamdom,domevents\"","markup1","youtube","presentation"]},"alesya-polovets":{"github":"https://github.com/alesya-polovets","tasks":["codejamcv\"","codejamcorejs\"","markup1","codejamdom,domevents\""]},"geek10010":{"github":"https://github.com/geek10010","tasks":["codejamcv\"","codejamcorejs\"","codejamdom,domevents\"","markup1","youtube","codejamscoreboard\""]},"antonykor":{"github":"https://github.com/antonykor","tasks":["codejamcv\"","codejamcorejs\"","codejamdom,domevents\"","markup1","youtube","codejamscoreboard\"","presentation"]},"saniok017":{"github":"https://github.com/saniok017","tasks":["codejamcv\"","codejamcorejs\"","codejamdom,domevents\"","markup1","youtube","presentation"]},"dzmitryalfer":{"github":"https://github.com/dzmitryalfer","tasks":[]}}},"elkinny":{"name":"viktoryia budzionnaya","github":"https://github.com/elkinny","students":{"kottanakor":{"github":"https://github.com/kottanakor","tasks":["codejamcorejs\"","markup1"]},"daryazel":{"github":"https://github.com/daryazel","tasks":[]},"alenakharytonchyk":{"github":"https://github.com/alenakharytonchyk","tasks":["codejamcorejs\"","markup1","codejamcv\"","presentation","codejamdom,domevents\"","codejamdom,domevents\"","youtube"]},"drizzlman":{"github":"https://github.com/drizzlman","tasks":[]},"yonguksaram":{"github":"https://github.com/yonguksaram","tasks":["codejamcorejs\"","markup1"]}}},"den-bozhyk":{"name":"denis bozhyk","github":"https://github.com/den-bozhyk","students":{"mailikey":{"github":"https://github.com/mailikey","tasks":[]},"vladesco":{"github":"https://github.com/vladesco","tasks":["codejamcv\"","codejamdom,domevents\"","codejamcorejs\"","markup1","youtube","presentation","codejamscoreboard\""]},"drdiman":{"github":"https://github.com/drdiman","tasks":["codejamcv\"","codejamdom,domevents\"","codejamcorejs\"","markup1","youtube","presentation","codejamscoreboard\""]},"dzmitrymashuk":{"github":"https://github.com/dzmitrymashuk","tasks":[]},"ipixby":{"github":"https://github.com/ipixby","tasks":[]},"nickprudnik":{"github":"https://github.com/nickprudnik","tasks":[]},"vitalitybo":{"github":"https://github.com/vitalitybo","tasks":[]}}},"kbirulia":{"name":"katsiaryna birulia","github":"https://github.com/kbirulia","students":{"vergonini":{"github":"https://github.com/vergonini","tasks":[]},"katiar":{"github":"https://github.com/katiar","tasks":["codejamcv\"","codejamcorejs\"","markup1","codejamdom,domevents\"","youtube","presentation","codejamscoreboard\""]},"anaumovich":{"github":"https://github.com/anaumovich","tasks":[]},"kirillkolesnik123":{"github":"https://github.com/kirillkolesnik123","tasks":[]}}},"bezakdenis":{"name":"denis bezak","github":"https://github.com/BezakDenis","students":{"aleks210219":{"github":"https://github.com/aleks210219","tasks":[]},"krlktv":{"github":"https://github.com/krlktv","tasks":[]},"dsv-sergey":{"github":"https://github.com/dsv-sergey","tasks":["codejamcorejs\""]},"nadezhda-kotova":{"github":"https://github.com/nadezhda-kotova","tasks":[]},"alexalizurchik":{"github":"https://github.com/alexalizurchik","tasks":["codejamcv\""]},"pavellyolya":{"github":"https://github.com/pavellyolya","tasks":["codejamcorejs\"","codejamcv\"","markup1","codejamdom,domevents\"","codejamdom,domevents\"","markup1"]}}},"toshabely":{"name":"anton bely","github":"https://github.com/ToshaBely","students":{"arkhipenka":{"github":"https://github.com/arkhipenka","tasks":["markup1","youtube"]},"abespolov":{"github":"https://github.com/abespolov","tasks":["codejamcv\"","codejamcorejs\""]},"zzhiharevich":{"github":"https://github.com/zzhiharevich","tasks":[]},"dimaspivas":{"github":"https://github.com/dimaspivas","tasks":["codejamcorejs\""]},"maxkonopelko":{"github":"https://github.com/maxkonopelko","tasks":[]}}},"belousova-natallia":{"name":"natallia belavusava","github":"https://github.com/belousova-natallia","students":{"garnich":{"github":"https://github.com/garnich","tasks":["codejamcv\"","codejamcorejs\"","markup1","codejamdom,domevents\"","youtube","presentation","codejamscoreboard\""]},"altobeyk":{"github":"https://github.com/altobeyk","tasks":[]},"stigmatory15":{"github":"https://github.com/stigmatory15","tasks":["markup1","codejamcv\"","codejamcorejs\"","codejamdom,domevents\""]},"kmetkokate":{"github":"https://github.com/kmetkokate","tasks":[]}}},"tomasspring":{"name":"vera barysava","github":"https://github.com/TomasSpring","students":{"annakolesnikova":{"github":"https://github.com/annakolesnikova","tasks":["codejamcorejs\"","codejamcv\"","markup1","codejamdom,domevents\"","youtube","youtube","youtube"]},"eliendil":{"github":"https://github.com/eliendil","tasks":["codejamcorejs\"","codejamcv\"","markup1","codejamdom,domevents\"","presentation"]},"a11mo":{"github":"https://github.com/a11mo","tasks":[]},"thecobolt":{"github":"https://github.com/thecobolt","tasks":[]}}},"ximet":{"name":"dmitri bardt","github":"https://github.com/ximet","students":{"dianatsevan":{"github":"https://github.com/dianatsevan","tasks":[]},"christopher-0118":{"github":"https://github.com/christopher-0118","tasks":["codejamdom,domevents\"","codejamcorejs\""]},"happy-mary":{"github":"https://github.com/happy-mary","tasks":["markup1","codejamdom,domevents\"","codejamcorejs\"","codejamcorejs\"","codejamcv\""]},"onaker":{"github":"https://github.com/onaker","tasks":[]},"igorbyl":{"github":"https://github.com/igorbyl","tasks":["markup1","codejamdom,domevents\"","codejamcv\"","codejamcorejs\""]},"maksyermak":{"github":"https://github.com/maksyermak","tasks":["codejamcv\"","codejamcorejs\""]},"riba0017":{"github":"https://github.com/riba0017","tasks":[]}}},"tanya-bakhmatovich":{"name":"tatsiana bakhmatovich","github":"https://github.com/Tanya-Bakhmatovich","students":{"fogfug1":{"github":"https://github.com/fogfug1","tasks":["codejamcv\"","codejamcorejs\"","markup1","codejamdom,domevents\""]},"yauhenilyin":{"github":"https://github.com/yauhenilyin","tasks":[]},"dmitrigorchanin":{"github":"https://github.com/dmitrigorchanin","tasks":["codejamcorejs\"","markup1","codejamcv\"","codejamdom,domevents\""]},"soundmafi":{"github":"https://github.com/soundmafi","tasks":[]}}},"sintet":{"name":"dzmitry bahachuk","github":"https://github.com/sintet","students":{"aspowerr":{"github":"https://github.com/aspowerr","tasks":["codejamcv\"","codejamcorejs\"","markup1","presentation","youtube"]},"shchelkunchik":{"github":"https://github.com/shchelkunchik","tasks":[]},"thatcherrr":{"github":"https://github.com/thatcherrr","tasks":[]},"torioyoshiko":{"github":"https://github.com/torioyoshiko","tasks":[]},"julialar4enko":{"github":"https://github.com/julialar4enko","tasks":[]},"yasell":{"github":"https://github.com/yasell","tasks":[]},"aleksandrmedvedev9000":{"github":"https://github.com/aleksandrmedvedev9000","tasks":[]}}},"polinabobrovnik":{"name":"palina babrounik","github":"https://github.com/PolinaBobrovnik","students":{"wowprojeck":{"github":"https://github.com/wowprojeck","tasks":[]},"andvikvin":{"github":"https://github.com/andvikvin","tasks":["codejamcv\"","codejamcorejs\"","codejamdom,domevents\"","markup1","youtube","presentation"]},"alinkalu":{"github":"https://github.com/alinkalu","tasks":[]},"marry705":{"github":"https://github.com/marry705","tasks":["codejamcv\"","codejamcorejs\"","codejamdom,domevents\"","markup1","youtube","presentation"]},"fursaleksey":{"github":"https://github.com/fursaleksey","tasks":["codejamcv\"","codejamcorejs\"","codejamdom,domevents\"","markup1","youtube","presentation"]},"hursevichsergey":{"github":"https://github.com/hursevichsergey","tasks":[]}}},"sergeyshatter":{"name":"siarhei ausianik","github":"https://github.com/SergeyShatter","students":{"cuppake":{"github":"https://github.com/cuppake","tasks":["codejamcv\"","codejamcorejs\"","markup1","codejamdom,domevents\"","youtube","presentation","codejamscoreboard\""]},"pirsfrommi6":{"github":"https://github.com/pirsfrommi6","tasks":["codejamcorejs\"","codejamcv\"","rsactivist","markup1"]},"luffi2539":{"github":"https://github.com/luffi2539","tasks":["codejamcorejs\"","codejamcv\"","markup1","codejamdom,domevents\"","rsactivist"]},"kirilltk":{"github":"https://github.com/kirilltk","tasks":["codejamcorejs\"","codejamcorejs\"","codejamcv\"","markup1","codejamdom,domevents\"","codejamdom,domevents\""]}}},"tr3v3r":{"name":"aliaksei astafyeu","github":"https://github.com/tr3v3r","students":{"bezchekera":{"github":"https://github.com/bezchekera","tasks":[]},"nadinaaa":{"github":"https://github.com/nadinaaa","tasks":["codejamdom,domevents\"","markup1","codejamcv\""]},"volunyshka":{"github":"https://github.com/volunyshka","tasks":[]},"grnkvch":{"github":"https://github.com/grnkvch","tasks":["codejamcorejs\"","codejamcv\"","markup1","codejamcv\"","codejamcorejs\"","codejamdom,domevents\"","youtube","presentation"]},"driliad":{"github":"https://github.com/driliad","tasks":[]},"yanamina":{"github":"https://github.com/yanamina","tasks":[]}}},"vinfinit":{"name":"uladzimir artsemenka","github":"https://github.com/vinfinit","students":{"egoncharov":{"github":"https://github.com/egoncharov","tasks":[]},"elostryy":{"github":"https://github.com/elostryy","tasks":[]},"eauheni":{"github":"https://github.com/eauheni","tasks":[]},"mikhailnakanechny":{"github":"https://github.com/mikhailnakanechny","tasks":["codejamdom,domevents\"","markup1","presentation","youtube"]},"maringoka":{"github":"https://github.com/maringoka","tasks":[]}}},"amelk9n":{"name":"aliaksandr amialkovich","github":"https://github.com/amelk9n","students":{"vitalur":{"github":"https://github.com/vitalur","tasks":["codejamcv\"","codejamcorejs\"","codejamdom,domevents\"","markup1","youtube","presentation","codejamscoreboard\""]},"jrzlve":{"github":"https://github.com/jrzlve","tasks":["codejamcv\"","codejamcorejs\"","codejamdom,domevents\"","markup1","youtube","presentation"]},"panikutysh":{"github":"https://github.com/panikutysh","tasks":["codejamcv\"","codejamcorejs\""]},"vlukyane":{"github":"https://github.com/vlukyane","tasks":[]}}},"alidzm":{"name":"dzmitry aliaksandrau","github":"https://github.com/alidzm","students":{"devbarden":{"github":"https://github.com/devbarden","tasks":["codejamcv\"","codejamcorejs\"","codejamdom,domevents\"","markup1","youtube","presentation","codejamscoreboard\""]},"nicklevkovich":{"github":"https://github.com/nicklevkovich","tasks":["codejamcv\"","codejamcorejs\"","markup1","codejamdom,domevents\"","youtube","presentation","presentation"]},"poiskull":{"github":"https://github.com/poiskull","tasks":["codejamcv\"","codejamcorejs\""]},"mrio1":{"github":"https://github.com/mrio1","tasks":["codejamcv\"","codejamcorejs\""]},"alexkashpor":{"github":"https://github.com/alexkashpor","tasks":[]},"dmsomov":{"github":"https://github.com/dmsomov","tasks":["codejamcv\"","codejamcorejs\""]}}},"juliaalaeva":{"name":"yuliia alaieva","github":"https://github.com/JuliaAlaeva","students":{"mariannagarbuzova":{"github":"https://github.com/mariannagarbuzova","tasks":[]},"pytniza":{"github":"https://github.com/pytniza","tasks":["codejamcv\"","codejamcorejs\"","markup1","codejamdom,domevents\"","youtube"]},"ronavea":{"github":"https://github.com/ronavea","tasks":["markup1","codejamcv\"","codejamcorejs\"","codejamdom,domevents\"","youtube","youtube","codejamscoreboard\""]},"ahrechushkin":{"github":"https://github.com/ahrechushkin","tasks":[]},"huriosity":{"github":"https://github.com/huriosity","tasks":[]}}},"viktoryiaverasava":{"name":"viktoryia verasava","github":"https://github.com/ViktoryiaVerasava","students":{"psychotheus":{"github":"https://github.com/psychotheus","tasks":[]},"lowershotower":{"github":"https://github.com/lowershotower","tasks":["codejamcorejs\"","codejamcv\"","codejamdom,domevents\""]},"bn1knb":{"github":"https://github.com/bn1knb","tasks":[]},"zerovers":{"github":"https://github.com/zerovers","tasks":["codejamcorejs\"","codejamcv\"","markup1","codejamdom,domevents\"","youtube","youtube","presentation","rsactivist","codejamscoreboard\"","rsactivist","rsactivist"]},"25kopek":{"github":"https://github.com/25kopek","tasks":[]}}},"stsepchanka":{"name":"tatsiana stsepchanka","github":"https://github.com/stsepchanka","students":{"max-violent":{"github":"https://github.com/max-violent","tasks":[]},"rick42morty":{"github":"https://github.com/rick42morty","tasks":["codejamcv\"","codejamcorejs\"","markup1","codejamdom,domevents\"","youtube","presentation","codejamscoreboard\"","presentation"]},"dloz":{"github":"https://github.com/dloz","tasks":[]},"scifsyh":{"github":"https://github.com/scifsyh","tasks":[]},"tgfrey":{"github":"https://github.com/tgfrey","tasks":[]}}},"mkinitcpio":{"name":"aliaksandr kazhamiaka","github":"https://github.com/mkinitcpio","students":{"slayer110":{"github":"https://github.com/slayer110","tasks":["codejamcorejs\"","codejamdom,domevents\""]},"quiquek007":{"github":"https://github.com/quiquek007","tasks":["markup1","codejamdom,domevents\"","codejamcorejs\"","codejamcv\"","presentation","youtube","rsactivist","codejamscoreboard\""]},"mohax-13":{"github":"https://github.com/mohax-13","tasks":["codejamdom,domevents\""]},"ksenia-ok":{"github":"https://github.com/ksenia-ok","tasks":["codejamcorejs\"","codejamdom,domevents\""]},"artsiom-zhuk":{"github":"https://github.com/artsiom-zhuk","tasks":["codejamcorejs\"","codejamdom,domevents\""]}}},"clainatomi-zero":{"name":"maksim kantsavy","github":"https://github.com/clainatomi-zero","students":{"alexandrshlyaeu":{"github":"https://github.com/alexandrshlyaeu","tasks":[]},"nicalas93":{"github":"https://github.com/nicalas93","tasks":[]},"vldmr1":{"github":"https://github.com/vldmr1","tasks":[]},"shinoby85":{"github":"https://github.com/shinoby85","tasks":[]}}},"famchankou":{"name":"aliaksandr famchankou","github":"https://github.com/famchankou","students":{"vladimirdobrik":{"github":"https://github.com/vladimirdobrik","tasks":[]},"tvorchud":{"github":"https://github.com/tvorchud","tasks":[]},"iharvypau":{"github":"https://github.com/iharvypau","tasks":[]},"vitalijsk":{"github":"https://github.com/vitalijsk","tasks":[]},"fcsm-andrei":{"github":"https://github.com/fcsm-andrei","tasks":[]}}},"artsiom-zhuk":{"name":"","github":"artsiom-zhuk","students":{"mkinitcpio":{"github":"https://github.com/mkinitcpio","tasks":["codejamcorejs\""]}}},"nemkev":{"name":"","github":"nemkev","students":{"shank111":{"github":"https://github.com/Shank111","tasks":["codejamcorejs\""]}}}}}